{
  "symbol": "DHI",
  "statement": "bs",
  "frequency": "quarterly",
  "timestamp": "2025-09-19T13:59:24.880525",
  "data": {
    "financials": [
      {
        "accountsPayable": 1388.8,
        "accruedLiability": 2807.2,
        "additionalPaidInCapital": 3536.7,
        "cashEquivalents": 2614,
        "cashShortTermInvestments": 2614,
        "commonStock": 4,
        "currentAssets": 29738.3,
        "currentLiabilities": 6061.2,
        "currentPortionLongTermDebt": 0.4,
        "goodwill": 163.5,
        "inventory": 26726.1,
        "liabilitiesShareholdersEquity": 36395.9,
        "longTermDebt": 5544.1,
        "minorityInterest": 540.1,
        "netDebt": 4634.7,
        "noteReceivableLongTerm": 2894.7,
        "otherAssets": 3035.4,
        "otherCurrentAssets": 106.8,
        "otherCurrentliabilities": 160.6,
        "otherLiabilities": 197.6,
        "otherLongTermAssets": 117.4,
        "period": "2025-06-30",
        "propertyPlantEquipment": 610.1,
        "retainedEarnings": 30254.5,
        "sharesOutstanding": 298.945,
        "shortTermDebt": 1704.2,
        "tangibleBookValueperShare": 79.9124,
        "totalAssets": 36395.9,
        "totalDebt": 7248.7,
        "totalEquity": 24052.9,
        "totalLiabilities": 12343,
        "totalReceivables": 291.4,
        "treasuryStock": -9742.3
      },
      {
        "accountsPayable": 1373.8,
        "accruedLiability": 2686,
        "additionalPaidInCapital": 3509.6,
        "cashEquivalents": 2471.4,
        "cashShortTermInvestments": 2471.4,
        "commonStock": 4,
        "currentAssets": 29419.8,
        "currentLiabilities": 5746.1,
        "currentPortionLongTermDebt": 154.4,
        "goodwill": 163.5,
        "inventory": 26482.4,
        "liabilitiesShareholdersEquity": 35690,
        "longTermDebt": 4916.6,
        "minorityInterest": 531.6,
        "netDebt": 4047,
        "noteReceivableLongTerm": 2581,
        "otherAssets": 2982.6,
        "otherCurrentAssets": 116.4,
        "otherCurrentliabilities": 84.5,
        "otherLiabilities": 168.6,
        "otherLongTermAssets": 121.3,
        "period": "2025-03-31",
        "propertyPlantEquipment": 585.3,
        "retainedEarnings": 29352.3,
        "sharesOutstanding": 308.6291,
        "shortTermDebt": 1447.4,
        "tangibleBookValueperShare": 78.2933,
        "totalAssets": 35690,
        "totalDebt": 6518.4,
        "totalEquity": 24327.1,
        "totalLiabilities": 11362.9,
        "totalReceivables": 349.6,
        "treasuryStock": -8538.8
      },
      {
        "accountsPayable": 1372.6,
        "accruedLiability": 2610.8,
        "additionalPaidInCapital": 3508.2,
        "cashEquivalents": 3050.1,
        "cashShortTermInvestments": 3050.1,
        "commonStock": 4,
        "currentAssets": 29508.7,
        "currentLiabilities": 5245.4,
        "currentPortionLongTermDebt": 154.1,
        "goodwill": 163.5,
        "inventory": 26080.5,
        "liabilitiesShareholdersEquity": 35029.7,
        "longTermDebt": 4156.7,
        "minorityInterest": 519,
        "netDebt": 2047.6,
        "noteReceivableLongTerm": 1915.9,
        "otherAssets": 2884.5,
        "otherCurrentAssets": 121.8,
        "otherCurrentliabilities": 321,
        "otherLiabilities": 164.7,
        "otherLongTermAssets": 146.3,
        "period": "2024-12-31",
        "propertyPlantEquipment": 574.3,
        "retainedEarnings": 28667.4,
        "sharesOutstanding": 317.6522,
        "shortTermDebt": 786.9,
        "tangibleBookValueperShare": 78.0111,
        "totalAssets": 35029.7,
        "totalDebt": 5097.7,
        "totalEquity": 24943.9,
        "totalLiabilities": 10085.8,
        "totalReceivables": 256.3,
        "treasuryStock": -7235.7
      },
      {
        "accountsPayable": 1345.5,
        "accruedLiability": 2703.1,
        "accumulatedDepreciation": -323,
        "additionalPaidInCapital": 3490.7,
        "cashEquivalents": 4516.4,
        "cashShortTermInvestments": 4516.4,
        "commonStock": 4,
        "currentAssets": 29841.4,
        "currentLiabilities": 6343.4,
        "currentPortionLongTermDebt": 633.6,
        "goodwill": 163.5,
        "inventory": 24903.2,
        "liabilitiesShareholdersEquity": 36104.3,
        "longTermDebt": 3750.3,
        "minorityInterest": 511.6,
        "netDebt": 1401.3,
        "noteReceivableLongTerm": 2595,
        "otherAssets": 2890.4,
        "otherCurrentAssets": 117.9,
        "otherCurrentliabilities": 127.4,
        "otherLiabilities": 186.2,
        "otherLongTermAssets": 195.1,
        "period": "2024-09-30",
        "propertyPlantEquipment": 582.4,
        "retainedEarnings": 27951,
        "sharesOutstanding": 324.0274,
        "shortTermDebt": 1533.8,
        "tangibleBookValueperShare": 77.6147,
        "totalAssets": 36104.3,
        "totalDebt": 5917.7,
        "totalEquity": 25312.8,
        "totalLiabilities": 10791.5,
        "totalReceivables": 303.9,
        "treasuryStock": -6132.9
      },
      {
        "accountsPayable": 1412.7,
        "accruedLiability": 2547.2,
        "additionalPaidInCapital": 3458.9,
        "cashEquivalents": 2992.3,
        "cashShortTermInvestments": 2992.3,
        "commonStock": 4,
        "currentAssets": 28944.8,
        "currentLiabilities": 5852.7,
        "currentPortionLongTermDebt": 0.4,
        "goodwill": 163.5,
        "inventory": 25536.1,
        "liabilitiesShareholdersEquity": 35151.4,
        "longTermDebt": 3999.2,
        "minorityInterest": 494.2,
        "netDebt": 2698.7,
        "noteReceivableLongTerm": 2689.7,
        "otherAssets": 2761.3,
        "otherCurrentAssets": 96.3,
        "otherCurrentliabilities": 201,
        "otherLiabilities": 148.8,
        "otherLongTermAssets": 184.3,
        "period": "2024-06-30",
        "propertyPlantEquipment": 571.3,
        "retainedEarnings": 26765.3,
        "sharesOutstanding": 327.3734,
        "shortTermDebt": 1691.4,
        "tangibleBookValueperShare": 74.8167,
        "totalAssets": 35151.4,
        "totalDebt": 5691,
        "totalEquity": 24656.5,
        "totalLiabilities": 10494.9,
        "totalReceivables": 320.1,
        "treasuryStock": -5571.7
      },
      {
        "accountsPayable": 1386.5,
        "accruedLiability": 2434.1,
        "additionalPaidInCapital": 3431.6,
        "cashEquivalents": 3063.1,
        "cashShortTermInvestments": 3063.1,
        "commonStock": 4,
        "currentAssets": 28325,
        "currentLiabilities": 6137.4,
        "currentPortionLongTermDebt": 221.5,
        "goodwill": 163.5,
        "inventory": 24840,
        "liabilitiesShareholdersEquity": 34398.2,
        "longTermDebt": 3832.4,
        "minorityInterest": 480.9,
        "netDebt": 2874.8,
        "noteReceivableLongTerm": 2776.3,
        "otherAssets": 2573.7,
        "otherCurrentAssets": 98.1,
        "otherCurrentliabilities": 211.3,
        "otherLiabilities": 132,
        "otherLongTermAssets": 196.8,
        "period": "2024-03-31",
        "propertyPlantEquipment": 526.4,
        "retainedEarnings": 25510.2,
        "sharesOutstanding": 330.1963,
        "shortTermDebt": 1884,
        "tangibleBookValueperShare": 71.6301,
        "totalAssets": 34398.2,
        "totalDebt": 5937.9,
        "totalEquity": 23815.5,
        "totalLiabilities": 10582.7,
        "totalReceivables": 323.8,
        "treasuryStock": -5130.3
      },
      {
        "accountsPayable": 1260.3,
        "accruedLiability": 2295.1,
        "additionalPaidInCapital": 3440.2,
        "cashEquivalents": 3323.4,
        "cashShortTermInvestments": 3323.4,
        "commonStock": 4,
        "currentAssets": 27769.9,
        "currentLiabilities": 5689.4,
        "currentPortionLongTermDebt": 214.6,
        "goodwill": 163.5,
        "inventory": 24050.3,
        "liabilitiesShareholdersEquity": 33381.6,
        "longTermDebt": 3796.1,
        "minorityInterest": 450.1,
        "netDebt": 1967,
        "noteReceivableLongTerm": 2142,
        "otherAssets": 2753.8,
        "otherCurrentAssets": 100.8,
        "otherCurrentliabilities": 639.7,
        "otherLiabilities": 292.6,
        "otherLongTermAssets": 197.1,
        "period": "2023-12-31",
        "propertyPlantEquipment": 518.8,
        "retainedEarnings": 24437.3,
        "sharesOutstanding": 332.1903,
        "shortTermDebt": 1279.7,
        "tangibleBookValueperShare": 69.207,
        "totalAssets": 33381.6,
        "totalDebt": 5290.4,
        "totalEquity": 23153.4,
        "totalLiabilities": 10228.2,
        "totalReceivables": 295.4,
        "treasuryStock": -4728.1
      },
      {
        "accountsPayable": 1246.2,
        "accruedLiability": 2440.7,
        "accumulatedDepreciation": -299.2,
        "additionalPaidInCapital": 3432.2,
        "cashEquivalents": 3873.6,
        "cashShortTermInvestments": 3873.6,
        "commonStock": 4,
        "currentAssets": 26672.9,
        "currentLiabilities": 5927.4,
        "currentPortionLongTermDebt": 190,
        "goodwill": 163.5,
        "inventory": 22373.3,
        "liabilitiesShareholdersEquity": 32582.4,
        "longTermDebt": 3234.9,
        "minorityInterest": 441.7,
        "netDebt": 1220.9,
        "noteReceivableLongTerm": 2613.8,
        "otherAssets": 2590,
        "otherCurrentAssets": 93,
        "otherCurrentliabilities": 380.9,
        "otherLiabilities": 282.2,
        "otherLongTermAssets": 213.7,
        "period": "2023-09-30",
        "propertyPlantEquipment": 492,
        "retainedEarnings": 23589.8,
        "sharesOutstanding": 334.8486,
        "shortTermDebt": 1669.6,
        "tangibleBookValueperShare": 67.2922,
        "totalAssets": 32582.4,
        "totalDebt": 5094.5,
        "totalEquity": 22696.2,
        "totalLiabilities": 9886.2,
        "totalReceivables": 333,
        "treasuryStock": -4329.8
      },
      {
        "accountsPayable": 1369.5,
        "accruedLiability": 2248.9,
        "additionalPaidInCapital": 3394.7,
        "cashEquivalents": 3379.1,
        "cashShortTermInvestments": 3379.1,
        "commonStock": 4,
        "currentAssets": 26736.6,
        "currentLiabilities": 6139.2,
        "currentPortionLongTermDebt": 538.5,
        "goodwill": 163.5,
        "inventory": 22983.5,
        "liabilitiesShareholdersEquity": 32323.1,
        "longTermDebt": 3881.2,
        "minorityInterest": 425.9,
        "netDebt": 2726.2,
        "noteReceivableLongTerm": 2499.9,
        "otherAssets": 2400.3,
        "otherCurrentAssets": 58.1,
        "otherCurrentliabilities": 296.7,
        "otherLiabilities": 220.4,
        "otherLongTermAssets": 216.6,
        "period": "2023-06-30",
        "propertyPlantEquipment": 469.7,
        "retainedEarnings": 22164.4,
        "sharesOutstanding": 338.223,
        "shortTermDebt": 1685.6,
        "tangibleBookValueperShare": 63.5465,
        "totalAssets": 32323.1,
        "totalDebt": 6105.3,
        "totalEquity": 21656.4,
        "totalLiabilities": 10666.7,
        "totalReceivables": 315.9,
        "treasuryStock": -3906.7
      },
      {
        "accountsPayable": 1251.3,
        "accruedLiability": 2170.9,
        "additionalPaidInCapital": 3358,
        "cashEquivalents": 3051.1,
        "cashShortTermInvestments": 3051.1,
        "commonStock": 4,
        "currentAssets": 25988.2,
        "currentLiabilities": 6069.2,
        "currentPortionLongTermDebt": 590.5,
        "goodwill": 163.5,
        "inventory": 22571.7,
        "liabilitiesShareholdersEquity": 31170.8,
        "longTermDebt": 3821.5,
        "minorityInterest": 409.1,
        "netDebt": 2915.8,
        "noteReceivableLongTerm": 2201.3,
        "otherAssets": 2292.5,
        "otherCurrentAssets": 83.1,
        "otherCurrentliabilities": 501.6,
        "otherLiabilities": 158.3,
        "otherLongTermAssets": 135.8,
        "period": "2023-03-31",
        "propertyPlantEquipment": 553,
        "retainedEarnings": 20914.5,
        "sharesOutstanding": 341.0703,
        "shortTermDebt": 1554.9,
        "tangibleBookValueperShare": 60.2492,
        "totalAssets": 31170.8,
        "totalDebt": 5966.9,
        "totalEquity": 20712.7,
        "totalLiabilities": 10458.1,
        "totalReceivables": 282.3,
        "treasuryStock": -3563.8
      },
      {
        "accountsPayable": 1205,
        "accruedLiability": 2097.2,
        "additionalPaidInCapital": 3352,
        "cashEquivalents": 2591.1,
        "cashShortTermInvestments": 2591.1,
        "commonStock": 4,
        "currentAssets": 25442.5,
        "currentLiabilities": 5967.3,
        "currentPortionLongTermDebt": 881.3,
        "goodwill": 163.5,
        "inventory": 22445.3,
        "liabilitiesShareholdersEquity": 30264.5,
        "longTermDebt": 3595.1,
        "minorityInterest": 399.1,
        "netDebt": 3099.2,
        "noteReceivableLongTerm": 1858.5,
        "otherAssets": 2255.9,
        "otherCurrentAssets": 88.1,
        "otherCurrentliabilities": 569.9,
        "otherLiabilities": 149.7,
        "otherLongTermAssets": 159.3,
        "period": "2022-12-31",
        "propertyPlantEquipment": 548.3,
        "retainedEarnings": 20057.9,
        "sharesOutstanding": 343.2786,
        "shortTermDebt": 1213.9,
        "tangibleBookValueperShare": 58.232,
        "totalAssets": 30264.5,
        "totalDebt": 5690.3,
        "totalEquity": 20153.3,
        "totalLiabilities": 10111.2,
        "totalReceivables": 318,
        "treasuryStock": -3260.6
      },
      {
        "accountsPayable": 1360.3,
        "accruedLiability": 2436.6,
        "additionalPaidInCapital": 3349.5,
        "cashEquivalents": 2540.5,
        "cashShortTermInvestments": 2540.5,
        "commonStock": 4,
        "currentAssets": 24622.4,
        "currentLiabilities": 6605.4,
        "currentPortionLongTermDebt": 855.1,
        "goodwill": 163.5,
        "inventory": 21655.7,
        "liabilitiesShareholdersEquity": 30351.1,
        "longTermDebt": 3593.5,
        "minorityInterest": 389.3,
        "netDebt": 3526.4,
        "noteReceivableLongTerm": 2460.3,
        "otherAssets": 2576.7,
        "otherCurrentAssets": 77.4,
        "otherCurrentliabilities": 335.1,
        "otherLiabilities": 366.6,
        "otherLongTermAssets": 173.5,
        "period": "2022-09-30",
        "propertyPlantEquipment": 518.2,
        "retainedEarnings": 19185.3,
        "sharesOutstanding": 343.953,
        "shortTermDebt": 1618.3,
        "tangibleBookValueperShare": 55.9169,
        "totalAssets": 30351.1,
        "totalDebt": 6066.9,
        "totalEquity": 19396.3,
        "totalLiabilities": 10954.8,
        "totalReceivables": 348.8,
        "treasuryStock": -3142.5
      },
      {
        "accountsPayable": 1507.3,
        "accruedLiability": 2018.1,
        "additionalPaidInCapital": 3317.7,
        "cashEquivalents": 1655.7,
        "cashShortTermInvestments": 1655.7,
        "commonStock": 4,
        "currentAssets": 23742.6,
        "currentLiabilities": 6096.8,
        "currentPortionLongTermDebt": 437.9,
        "goodwill": 163.5,
        "inventory": 21698.9,
        "liabilitiesShareholdersEquity": 28869.9,
        "longTermDebt": 4131.6,
        "minorityInterest": 373,
        "netDebt": 4319.5,
        "noteReceivableLongTerm": 2151.6,
        "otherAssets": 2265.7,
        "otherCurrentAssets": 93.1,
        "otherCurrentliabilities": 727.8,
        "otherLiabilities": 206,
        "otherLongTermAssets": 186,
        "period": "2022-06-30",
        "propertyPlantEquipment": 524,
        "retainedEarnings": 17631.6,
        "sharesOutstanding": 347.377,
        "shortTermDebt": 1405.7,
        "tangibleBookValueperShare": 51.5261,
        "totalAssets": 28869.9,
        "totalDebt": 5975.2,
        "totalEquity": 18062.5,
        "totalLiabilities": 10807.4,
        "totalReceivables": 294.9,
        "treasuryStock": -2890.8
      },
      {
        "accountsPayable": 1378.6,
        "accruedLiability": 1914.9,
        "additionalPaidInCapital": 3288.7,
        "cashEquivalents": 1663.9,
        "cashShortTermInvestments": 1663.9,
        "commonStock": 4,
        "currentAssets": 21851.1,
        "currentLiabilities": 5241.2,
        "currentPortionLongTermDebt": 436,
        "goodwill": 163.5,
        "inventory": 19846.5,
        "liabilitiesShareholdersEquity": 26685.3,
        "longTermDebt": 3991.1,
        "minorityInterest": 342.9,
        "netDebt": 3906.1,
        "noteReceivableLongTerm": 2307.6,
        "otherAssets": 1894,
        "otherCurrentAssets": 77.2,
        "otherCurrentliabilities": 368.8,
        "otherLiabilities": 335.2,
        "otherLongTermAssets": 156.9,
        "period": "2022-03-31",
        "propertyPlantEquipment": 475.7,
        "retainedEarnings": 16063,
        "sharesOutstanding": 351.9554,
        "shortTermDebt": 1142.9,
        "tangibleBookValueperShare": 47.1975,
        "totalAssets": 26685.3,
        "totalDebt": 5570,
        "totalEquity": 16774.9,
        "totalLiabilities": 9910.4,
        "totalReceivables": 263.5,
        "treasuryStock": -2580.8
      },
      {
        "accountsPayable": 1150.7,
        "accruedLiability": 1786.5,
        "additionalPaidInCapital": 3282.7,
        "cashEquivalents": 2442.1,
        "cashShortTermInvestments": 2442.1,
        "commonStock": 4,
        "currentAssets": 20976.3,
        "currentLiabilities": 5351.7,
        "currentPortionLongTermDebt": 505.8,
        "goodwill": 163.5,
        "inventory": 18202.5,
        "liabilitiesShareholdersEquity": 24999.4,
        "longTermDebt": 3489.5,
        "minorityInterest": 335.7,
        "netDebt": 2813.2,
        "noteReceivableLongTerm": 1894.1,
        "otherAssets": 1520.4,
        "otherCurrentAssets": 70.4,
        "otherCurrentliabilities": 648.7,
        "otherLiabilities": 144.8,
        "otherLongTermAssets": 160.1,
        "period": "2021-12-31",
        "propertyPlantEquipment": 448.5,
        "retainedEarnings": 14705.8,
        "sharesOutstanding": 354.2776,
        "shortTermDebt": 1260,
        "tangibleBookValueperShare": 43.7911,
        "totalAssets": 24999.4,
        "totalDebt": 5255.3,
        "totalEquity": 15677.7,
        "totalLiabilities": 9321.7,
        "totalReceivables": 261.3,
        "treasuryStock": -2314.8
      },
      {
        "accountsPayable": 1177,
        "accruedLiability": 1826.6,
        "accumulatedDepreciation": -305,
        "additionalPaidInCapital": 3274.8,
        "cashEquivalents": 3210.4,
        "cashShortTermInvestments": 3210.4,
        "commonStock": 4,
        "currentAssets": 20004.2,
        "currentLiabilities": 5209.3,
        "currentPortionLongTermDebt": 429.5,
        "goodwill": 163.5,
        "inventory": 16479.1,
        "liabilitiesShareholdersEquity": 24015.9,
        "longTermDebt": 3488.3,
        "minorityInterest": 329.7,
        "netDebt": 2202,
        "noteReceivableLongTerm": 2085.9,
        "otherAssets": 1315.2,
        "otherCurrentAssets": 51.6,
        "otherCurrentliabilities": 281.6,
        "otherLiabilities": 102.1,
        "otherLongTermAssets": 182.1,
        "period": "2021-09-30",
        "propertyPlantEquipment": 428.5,
        "retainedEarnings": 13644.3,
        "sharesOutstanding": 356.0158,
        "shortTermDebt": 1494.6,
        "tangibleBookValueperShare": 41.3549,
        "totalAssets": 24015.9,
        "totalDebt": 5412.4,
        "totalEquity": 14886.5,
        "totalLiabilities": 9129.4,
        "totalReceivables": 263.1,
        "treasuryStock": -2036.6
      },
      {
        "accountsPayable": 1250.9,
        "accruedLiability": 1642.1,
        "accumulatedDepreciation": -295,
        "additionalPaidInCapital": 3246,
        "cashEquivalents": 1942.7,
        "cashShortTermInvestments": 1942.7,
        "commonStock": 4,
        "currentAssets": 18259.5,
        "currentLiabilities": 4656.5,
        "currentPortionLongTermDebt": 429.5,
        "goodwill": 163.5,
        "inventory": 16011.7,
        "liabilitiesShareholdersEquity": 21793.5,
        "longTermDebt": 2893.2,
        "minorityInterest": 322.1,
        "netDebt": 2473.6,
        "noteReceivableLongTerm": 1698.7,
        "otherAssets": 1259.8,
        "otherCurrentAssets": 54.7,
        "otherCurrentliabilities": 240.4,
        "otherLiabilities": 118.8,
        "otherLongTermAssets": 173.5,
        "period": "2021-06-30",
        "propertyPlantEquipment": 402,
        "retainedEarnings": 12376.9,
        "sharesOutstanding": 358.1248,
        "shortTermDebt": 1093.6,
        "tangibleBookValueperShare": 38.0856,
        "totalAssets": 21793.5,
        "totalDebt": 4416.3,
        "totalEquity": 13802.9,
        "totalLiabilities": 7990.6,
        "totalReceivables": 250.4,
        "treasuryStock": -1824
      },
      {
        "accountsPayable": 1137,
        "accruedLiability": 1574,
        "accumulatedDepreciation": -303,
        "additionalPaidInCapital": 3208,
        "cashEquivalents": 2205,
        "cashShortTermInvestments": 2205,
        "commonStock": 4,
        "currentAssets": 16990,
        "currentLiabilities": 4745,
        "currentPortionLongTermDebt": 425,
        "goodwill": 164,
        "inventory": 14476,
        "liabilitiesShareholdersEquity": 21084,
        "longTermDebt": 2844,
        "minorityInterest": 313,
        "netDebt": 2267,
        "noteReceivableLongTerm": 1807,
        "otherAssets": 1189,
        "otherCurrentAssets": 52,
        "otherCurrentliabilities": 405,
        "otherLiabilities": 219,
        "otherLongTermAssets": 170,
        "period": "2021-03-31",
        "propertyPlantEquipment": 929,
        "retainedEarnings": 11334,
        "sharesOutstanding": 360,
        "shortTermDebt": 1204,
        "tangibleBookValueperShare": 35.5528,
        "totalAssets": 21084,
        "totalDebt": 4472,
        "totalEquity": 12963,
        "totalLiabilities": 8121,
        "totalReceivables": 257,
        "treasuryStock": -1583
      },
      {
        "accountsPayable": 846,
        "accruedLiability": 1352,
        "accumulatedDepreciation": -294,
        "additionalPaidInCapital": 3237,
        "cashEquivalents": 2455,
        "cashShortTermInvestments": 2455,
        "commonStock": 4,
        "currentAssets": 16313,
        "currentLiabilities": 3973,
        "currentPortionLongTermDebt": 414,
        "goodwill": 164,
        "inventory": 13577,
        "liabilitiesShareholdersEquity": 19780,
        "longTermDebt": 2842,
        "minorityInterest": 285,
        "netDebt": 1771,
        "noteReceivableLongTerm": 1488,
        "otherAssets": 1037,
        "otherCurrentAssets": 53,
        "otherCurrentliabilities": 392,
        "otherLiabilities": 195,
        "otherLongTermAssets": 162,
        "period": "2020-12-31",
        "propertyPlantEquipment": 782,
        "retainedEarnings": 10477,
        "sharesOutstanding": 364,
        "shortTermDebt": 969,
        "tangibleBookValueperShare": 33.8489,
        "totalAssets": 19780,
        "totalDebt": 4226,
        "totalEquity": 12485,
        "totalLiabilities": 7295,
        "totalReceivables": 228,
        "treasuryStock": -1232
      },
      {
        "accountsPayable": 901,
        "accruedLiability": 1336,
        "accumulatedDepreciation": -284,
        "additionalPaidInCapital": 3241,
        "cashEquivalents": 3019,
        "cashShortTermInvestments": 3019,
        "commonStock": 4,
        "currentAssets": 15526,
        "currentLiabilities": 3973,
        "currentPortionLongTermDebt": 467,
        "goodwill": 164,
        "inventory": 12237,
        "liabilitiesShareholdersEquity": 18912,
        "longTermDebt": 2684,
        "minorityInterest": 282,
        "netDebt": 1264,
        "noteReceivableLongTerm": 1576,
        "otherAssets": 926,
        "otherCurrentAssets": 46,
        "otherCurrentliabilities": 136,
        "otherLiabilities": 135,
        "otherLongTermAssets": 167,
        "period": "2020-09-30",
        "propertyPlantEquipment": 718,
        "retainedEarnings": 9758,
        "sharesOutstanding": 364,
        "shortTermDebt": 1133,
        "tangibleBookValueperShare": 32.0769,
        "totalAssets": 18912,
        "totalDebt": 4283,
        "totalEquity": 11840,
        "totalLiabilities": 7072,
        "totalReceivables": 224,
        "treasuryStock": -1163
      },
      {
        "accountsPayable": 761,
        "accruedLiability": 1211,
        "accumulatedDepreciation": -289,
        "additionalPaidInCapital": 3214,
        "cashEquivalents": 2354,
        "cashShortTermInvestments": 2354,
        "commonStock": 4,
        "currentAssets": 14741,
        "currentLiabilities": 3831,
        "currentPortionLongTermDebt": 444,
        "goodwill": 164,
        "inventory": 12139,
        "liabilitiesShareholdersEquity": 17974,
        "longTermDebt": 2680,
        "minorityInterest": 279,
        "netDebt": 1943,
        "noteReceivableLongTerm": 1548,
        "otherAssets": 842,
        "otherCurrentAssets": 35,
        "otherCurrentliabilities": 242,
        "otherLiabilities": 135,
        "otherLongTermAssets": 178,
        "period": "2020-06-30",
        "propertyPlantEquipment": 667,
        "retainedEarnings": 8993,
        "sharesOutstanding": 364,
        "shortTermDebt": 1173,
        "tangibleBookValueperShare": 29.9011,
        "totalAssets": 17974,
        "totalDebt": 4297,
        "totalEquity": 11048,
        "totalLiabilities": 6926,
        "totalReceivables": 213,
        "treasuryStock": -1163
      },
      {
        "accountsPayable": 707,
        "accruedLiability": 1118,
        "accumulatedDepreciation": -276,
        "additionalPaidInCapital": 3191,
        "cashEquivalents": 1523,
        "cashShortTermInvestments": 1523,
        "commonStock": 4,
        "currentAssets": 13985,
        "currentLiabilities": 3536,
        "currentPortionLongTermDebt": 436,
        "goodwill": 164,
        "inventory": 12225,
        "liabilitiesShareholdersEquity": 17130,
        "longTermDebt": 2684,
        "minorityInterest": 277,
        "netDebt": 2784,
        "noteReceivableLongTerm": 1422,
        "otherAssets": 933,
        "otherCurrentAssets": 48,
        "otherCurrentliabilities": 88,
        "otherLiabilities": 175,
        "otherLongTermAssets": 164,
        "period": "2020-03-31",
        "propertyPlantEquipment": 628,
        "retainedEarnings": 8425,
        "sharesOutstanding": 364,
        "shortTermDebt": 1187,
        "tangibleBookValueperShare": 28.2802,
        "totalAssets": 17130,
        "totalDebt": 4307,
        "totalEquity": 10458,
        "totalLiabilities": 6672,
        "totalReceivables": 189,
        "treasuryStock": -1163
      },
      {
        "accountsPayable": 659,
        "accruedLiability": 1106,
        "accumulatedDepreciation": -260,
        "additionalPaidInCapital": 3182,
        "cashEquivalents": 1583,
        "cashShortTermInvestments": 1583,
        "commonStock": 4,
        "currentAssets": 13713,
        "currentLiabilities": 3833,
        "currentPortionLongTermDebt": 1046,
        "goodwill": 164,
        "inventory": 11899,
        "liabilitiesShareholdersEquity": 16323,
        "longTermDebt": 1888,
        "minorityInterest": 276,
        "netDebt": 2200,
        "noteReceivableLongTerm": 1066,
        "otherAssets": 778,
        "otherCurrentAssets": 59,
        "otherCurrentliabilities": 172,
        "otherLiabilities": 99,
        "otherLongTermAssets": 167,
        "period": "2019-12-31",
        "propertyPlantEquipment": 600,
        "retainedEarnings": 8007,
        "sharesOutstanding": 366,
        "shortTermDebt": 850,
        "tangibleBookValueperShare": 27.4945,
        "totalAssets": 16323,
        "totalDebt": 3783,
        "totalEquity": 10227,
        "totalLiabilities": 6096,
        "totalReceivables": 172,
        "treasuryStock": -965
      },
      {
        "accountsPayable": 634,
        "accruedLiability": 1092,
        "additionalPaidInCapital": 3179,
        "cashEquivalents": 1494,
        "cashShortTermInvestments": 1494,
        "commonStock": 4,
        "currentAssets": 13005,
        "currentLiabilities": 3422,
        "currentPortionLongTermDebt": 716,
        "goodwill": 164,
        "inventory": 11282,
        "liabilitiesShareholdersEquity": 15607,
        "longTermDebt": 1794,
        "longTermInvestments": 7,
        "minorityInterest": 274,
        "netDebt": 1905,
        "noteReceivableLongTerm": 1111,
        "otherAssets": 811,
        "otherCurrentAssets": 50,
        "otherCurrentliabilities": 91,
        "otherLiabilities": 95,
        "otherLongTermAssets": 212,
        "period": "2019-09-30",
        "propertyPlantEquipment": 462,
        "retainedEarnings": 7640,
        "sharesOutstanding": 368,
        "shortTermDebt": 889,
        "tangibleBookValueperShare": 26.7853,
        "totalAssets": 15607,
        "totalDebt": 3399,
        "totalEquity": 10021,
        "totalLiabilities": 5586,
        "totalReceivables": 179,
        "treasuryStock": -802
      },
      {
        "accountsPayable": 681,
        "accruedLiability": 1038,
        "additionalPaidInCapital": 3146,
        "cashEquivalents": 864,
        "cashShortTermInvestments": 864,
        "commonStock": 4,
        "currentAssets": 12777,
        "currentLiabilities": 3347,
        "currentPortionLongTermDebt": 711,
        "goodwill": 164,
        "inventory": 11702,
        "liabilitiesShareholdersEquity": 15224,
        "longTermDebt": 1943,
        "minorityInterest": 172,
        "netDebt": 2587,
        "noteReceivableLongTerm": 991,
        "otherAssets": 806,
        "otherCurrentAssets": 34,
        "otherCurrentliabilities": 120,
        "otherLiabilities": 120,
        "otherLongTermAssets": 195,
        "period": "2019-06-30",
        "propertyPlantEquipment": 454,
        "retainedEarnings": 7190,
        "sharesOutstanding": 370,
        "shortTermDebt": 797,
        "tangibleBookValueperShare": 25.6162,
        "totalAssets": 15224,
        "totalDebt": 3451,
        "totalEquity": 9642,
        "totalLiabilities": 5582,
        "totalReceivables": 177,
        "treasuryStock": -698
      },
      {
        "accountsPayable": 659,
        "accruedLiability": 954,
        "additionalPaidInCapital": 3123,
        "cashEquivalents": 699,
        "cashShortTermInvestments": 699,
        "commonStock": 4,
        "currentAssets": 12786,
        "currentLiabilities": 3150,
        "currentPortionLongTermDebt": 700,
        "goodwill": 164,
        "inventory": 11920,
        "liabilitiesShareholdersEquity": 15007,
        "longTermDebt": 2232,
        "minorityInterest": 174,
        "netDebt": 2923,
        "noteReceivableLongTerm": 831,
        "otherAssets": 748,
        "otherCurrentAssets": 31,
        "otherCurrentliabilities": 146,
        "otherLiabilities": 92,
        "otherLongTermAssets": 204,
        "period": "2019-03-31",
        "propertyPlantEquipment": 438,
        "retainedEarnings": 6772,
        "sharesOutstanding": 373,
        "shortTermDebt": 691,
        "tangibleBookValueperShare": 24.6542,
        "totalAssets": 15007,
        "totalDebt": 3622,
        "totalEquity": 9360,
        "totalLiabilities": 5647,
        "totalReceivables": 136,
        "treasuryStock": -539
      },
      {
        "accountsPayable": 697,
        "accruedLiability": 927,
        "additionalPaidInCapital": 3108,
        "cashEquivalents": 737,
        "cashShortTermInvestments": 737,
        "commonStock": 4,
        "currentAssets": 12500,
        "currentLiabilities": 3897,
        "currentPortionLongTermDebt": 1122,
        "goodwill": 158,
        "inventory": 11596,
        "liabilitiesShareholdersEquity": 14536,
        "longTermDebt": 1247,
        "minorityInterest": 174,
        "netDebt": 2605,
        "noteReceivableLongTerm": 656,
        "otherAssets": 732,
        "otherCurrentAssets": 36,
        "otherCurrentliabilities": 177,
        "otherLiabilities": 94,
        "otherLongTermAssets": 256,
        "period": "2018-12-31",
        "propertyPlantEquipment": 391,
        "retainedEarnings": 6476,
        "sharesOutstanding": 373,
        "shortTermDebt": 974,
        "tangibleBookValueperShare": 24.0402,
        "totalAssets": 14536,
        "totalDebt": 3342,
        "totalEquity": 9125,
        "totalLiabilities": 5411,
        "totalReceivables": 131,
        "treasuryStock": -463
      },
      {
        "accountsPayable": 625,
        "accruedLiability": 961,
        "additionalPaidInCapital": 3085,
        "cashEquivalents": 1473,
        "cashShortTermInvestments": 1473,
        "commonStock": 4,
        "currentAssets": 12041,
        "currentLiabilities": 2822,
        "currentPortionLongTermDebt": 505,
        "goodwill": 109,
        "inventory": 10395,
        "liabilitiesShareholdersEquity": 14115,
        "longTermDebt": 2061,
        "longTermInvestments": 11,
        "minorityInterest": 175,
        "netDebt": 1731,
        "noteReceivableLongTerm": 796,
        "otherAssets": 638,
        "otherCurrentAssets": 37,
        "otherCurrentliabilities": 93,
        "otherLiabilities": 73,
        "otherLongTermAssets": 227,
        "period": "2018-09-30",
        "propertyPlantEquipment": 401,
        "retainedEarnings": 6218,
        "sharesOutstanding": 376,
        "shortTermDebt": 638,
        "tangibleBookValueperShare": 23.6037,
        "totalAssets": 14115,
        "totalDebt": 3204,
        "totalEquity": 8984,
        "totalLiabilities": 5130,
        "totalReceivables": 136,
        "treasuryStock": -322
      },
      {
        "accountsPayable": 655,
        "accruedLiability": 885,
        "additionalPaidInCapital": 3064,
        "cashEquivalents": 1178,
        "cashShortTermInvestments": 1178,
        "commonStock": 4,
        "currentAssets": 11640,
        "currentLiabilities": 2673,
        "currentPortionLongTermDebt": 506,
        "goodwill": 109,
        "inventory": 10303,
        "liabilitiesShareholdersEquity": 13593,
        "longTermDebt": 2061,
        "longTermInvestments": 32,
        "minorityInterest": 173,
        "netDebt": 1916,
        "noteReceivableLongTerm": 680,
        "otherAssets": 592,
        "otherCurrentAssets": 19,
        "otherCurrentliabilities": 101,
        "otherLiabilities": 88,
        "otherLongTermAssets": 263,
        "period": "2018-06-30",
        "propertyPlantEquipment": 385,
        "retainedEarnings": 5799,
        "sharesOutstanding": 377,
        "shortTermDebt": 526,
        "tangibleBookValueperShare": 22.5146,
        "totalAssets": 13593,
        "totalDebt": 3094,
        "totalEquity": 8597,
        "totalLiabilities": 4996,
        "totalReceivables": 140,
        "treasuryStock": -270
      },
      {
        "accountsPayable": 583,
        "accruedLiability": 874,
        "additionalPaidInCapital": 3046,
        "cashEquivalents": 1011,
        "cashShortTermInvestments": 1011,
        "commonStock": 4,
        "currentAssets": 11325,
        "currentLiabilities": 2521,
        "currentPortionLongTermDebt": 508,
        "goodwill": 109,
        "inventory": 10144,
        "liabilitiesShareholdersEquity": 13218,
        "longTermDebt": 2236,
        "longTermInvestments": 32,
        "minorityInterest": 173,
        "netDebt": 2223,
        "noteReceivableLongTerm": 658,
        "otherAssets": 546,
        "otherCurrentAssets": 23,
        "otherCurrentliabilities": 66,
        "otherLiabilities": 90,
        "otherLongTermAssets": 275,
        "period": "2018-03-31",
        "propertyPlantEquipment": 380,
        "retainedEarnings": 5392,
        "sharesOutstanding": 377,
        "shortTermDebt": 490,
        "tangibleBookValueperShare": 21.4589,
        "totalAssets": 13218,
        "totalDebt": 3234,
        "totalEquity": 8199,
        "totalLiabilities": 5019,
        "totalReceivables": 147,
        "treasuryStock": -243
      },
      {
        "accountsPayable": 576,
        "accruedLiability": 895,
        "additionalPaidInCapital": 3010,
        "cashEquivalents": 920,
        "cashShortTermInvestments": 920,
        "commonStock": 4,
        "currentAssets": 11145,
        "currentLiabilities": 2465,
        "currentPortionLongTermDebt": 520,
        "goodwill": 100,
        "inventory": 10040,
        "liabilitiesShareholdersEquity": 12957,
        "longTermDebt": 2350,
        "longTermInvestments": 86,
        "minorityInterest": 173,
        "netDebt": 2338,
        "noteReceivableLongTerm": 538,
        "otherAssets": 537,
        "otherCurrentAssets": 32,
        "otherCurrentliabilities": 86,
        "otherLiabilities": 88,
        "otherLongTermAssets": 293,
        "period": "2017-12-31",
        "propertyPlantEquipment": 358,
        "retainedEarnings": 5088,
        "sharesOutstanding": 376,
        "shortTermDebt": 388,
        "tangibleBookValueperShare": 20.6968,
        "totalAssets": 12957,
        "totalDebt": 3258,
        "totalEquity": 7882,
        "totalLiabilities": 5075,
        "totalReceivables": 153,
        "treasuryStock": -220
      },
      {
        "accountsPayable": 580,
        "accruedLiability": 878,
        "additionalPaidInCapital": 2992,
        "cashEquivalents": 1008,
        "cashShortTermInvestments": 1008,
        "commonStock": 4,
        "currentAssets": 10410,
        "currentLiabilities": 1898,
        "goodwill": 80,
        "inventory": 9237,
        "liabilitiesShareholdersEquity": 12185,
        "longTermDebt": 2452,
        "longTermInvestments": 0,
        "minorityInterest": 1,
        "netDebt": 1864,
        "noteReceivableLongTerm": 587,
        "otherAssets": 481,
        "otherCurrentAssets": 31,
        "otherCurrentliabilities": 20,
        "otherLiabilities": 87,
        "otherLongTermAssets": 382,
        "period": "2017-09-30",
        "propertyPlantEquipment": 325,
        "retainedEarnings": 4946,
        "sharesOutstanding": 375,
        "shortTermDebt": 420,
        "tangibleBookValueperShare": 20.4453,
        "totalAssets": 12185,
        "totalDebt": 2872,
        "totalEquity": 7747,
        "totalLiabilities": 4438,
        "totalReceivables": 134,
        "treasuryStock": -195
      },
      {
        "accountsPayable": 656,
        "accountsReceivables": 39,
        "accruedLiability": 886,
        "additionalPaidInCapital": 2957,
        "cashEquivalents": 512,
        "cashShortTermInvestments": 512,
        "commonStock": 4,
        "currentAssets": 10117,
        "currentLiabilities": 2051,
        "goodwill": 80,
        "inventory": 9554,
        "liabilitiesShareholdersEquity": 11977,
        "longTermDebt": 2453,
        "minorityInterest": 1,
        "netDebt": 2415,
        "noteReceivableLongTerm": 710,
        "otherAssets": 472,
        "otherCurrentAssets": 12,
        "otherCurrentliabilities": 36,
        "otherLiabilities": 36,
        "otherLongTermAssets": 395,
        "otherReceivables": 0,
        "period": "2017-06-30",
        "propertyPlantEquipment": 283,
        "retainedEarnings": 4670,
        "sharesOutstanding": 374,
        "shortTermDebt": 473,
        "tangibleBookValueperShare": 19.6684,
        "totalAssets": 11977,
        "totalDebt": 2927,
        "totalEquity": 7436,
        "totalLiabilities": 4541,
        "totalReceivables": 39,
        "treasuryStock": -195
      },
      {
        "accountsPayable": 581,
        "accountsReceivables": 32,
        "accruedLiability": 846,
        "additionalPaidInCapital": 2932,
        "cashEquivalents": 993,
        "cashShortTermInvestments": 993,
        "commonStock": 4,
        "currentAssets": 10083,
        "currentLiabilities": 1863,
        "goodwill": 80,
        "inventory": 9038,
        "liabilitiesShareholdersEquity": 11921,
        "longTermDebt": 2803,
        "minorityInterest": 1,
        "netDebt": 2229,
        "noteReceivableLongTerm": 663,
        "otherAssets": 465,
        "otherCurrentAssets": 20,
        "otherCurrentliabilities": 17,
        "otherLiabilities": 35,
        "otherLongTermAssets": 463,
        "otherReceivables": 0,
        "period": "2017-03-31",
        "propertyPlantEquipment": 248,
        "retainedEarnings": 4419,
        "sharesOutstanding": 376,
        "shortTermDebt": 419,
        "tangibleBookValueperShare": 18.9894,
        "totalAssets": 11921,
        "totalDebt": 3222,
        "totalEquity": 7220,
        "totalLiabilities": 4702,
        "totalReceivables": 32,
        "treasuryStock": -134
      },
      {
        "accountsPayable": 545,
        "accountsReceivables": 31,
        "accruedLiability": 833,
        "additionalPaidInCapital": 2885,
        "cashEquivalents": 1150,
        "cashShortTermInvestments": 1150,
        "commonStock": 4,
        "currentAssets": 9947,
        "currentLiabilities": 1898,
        "goodwill": 80,
        "inventory": 8742,
        "liabilitiesShareholdersEquity": 11712,
        "longTermDebt": 2799,
        "minorityInterest": 1,
        "netDebt": 2068,
        "noteReceivableLongTerm": 633,
        "otherAssets": 436,
        "otherCurrentAssets": 24,
        "otherCurrentliabilities": 101,
        "otherLiabilities": 34,
        "otherLongTermAssets": 477,
        "otherReceivables": 0,
        "period": "2016-12-31",
        "propertyPlantEquipment": 218,
        "retainedEarnings": 4227,
        "sharesOutstanding": 373,
        "shortTermDebt": 419,
        "tangibleBookValueperShare": 18.5013,
        "totalAssets": 11712,
        "totalDebt": 3218,
        "totalEquity": 6981,
        "totalLiabilities": 4731,
        "totalReceivables": 31,
        "treasuryStock": -134
      },
      {
        "accountsPayable": 578,
        "accountsReceivables": 36,
        "accruedLiability": 850,
        "additionalPaidInCapital": 2866,
        "cashEquivalents": 1303,
        "cashShortTermInvestments": 1303,
        "commonStock": 4,
        "currentAssets": 9710,
        "currentLiabilities": 1929,
        "goodwill": 80,
        "inventory": 8341,
        "liabilitiesShareholdersEquity": 11559,
        "longTermDebt": 2798,
        "minorityInterest": 1,
        "netDebt": 1968,
        "noteReceivableLongTerm": 743,
        "otherAssets": 426,
        "otherCurrentAssets": 30,
        "otherCurrentliabilities": 28,
        "otherEquity": 0,
        "otherLiabilities": 39,
        "otherLongTermAssets": 486,
        "otherReceivables": 0,
        "period": "2016-09-30",
        "propertyPlantEquipment": 195,
        "retainedEarnings": 4057,
        "sharesOutstanding": 373,
        "shortTermDebt": 473,
        "tangibleBookValueperShare": 17.9973,
        "totalAssets": 11559,
        "totalDebt": 3271,
        "totalEquity": 6793,
        "totalLiabilities": 4766,
        "totalReceivables": 36,
        "treasuryStock": -134
      },
      {
        "accountsPayable": 609,
        "accountsReceivables": 34,
        "accruedLiability": 839,
        "additionalPaidInCapital": 2839,
        "cashEquivalents": 907,
        "cashShortTermInvestments": 907,
        "commonStock": 4,
        "currentAssets": 9471,
        "currentLiabilities": 1988,
        "goodwill": 87,
        "inventory": 8504,
        "liabilitiesShareholdersEquity": 11333,
        "longTermDebt": 2797,
        "minorityInterest": 1,
        "netDebt": 2394,
        "noteReceivableLongTerm": 732,
        "otherAssets": 462,
        "otherCurrentAssets": 26,
        "otherCurrentliabilities": 36,
        "otherEquity": 0,
        "otherLiabilities": 35,
        "otherLongTermAssets": 517,
        "otherReceivables": 0,
        "period": "2016-06-30",
        "propertyPlantEquipment": 152,
        "retainedEarnings": 3803,
        "sharesOutstanding": 372,
        "shortTermDebt": 504,
        "tangibleBookValueperShare": 17.2715,
        "totalAssets": 11333,
        "totalDebt": 3301,
        "totalEquity": 6512,
        "totalLiabilities": 4821,
        "totalReceivables": 34,
        "treasuryStock": -134
      },
      {
        "accountsPayable": 542,
        "accountsReceivables": 25,
        "accruedLiability": 800,
        "additionalPaidInCapital": 2796,
        "cashEquivalents": 1224,
        "cashShortTermInvestments": 1224,
        "commonStock": 4,
        "currentAssets": 9492,
        "currentLiabilities": 1852,
        "goodwill": 87,
        "inventory": 8217,
        "liabilitiesShareholdersEquity": 11300,
        "longTermDebt": 3167,
        "minorityInterest": 1,
        "netDebt": 2439,
        "noteReceivableLongTerm": 717,
        "otherAssets": 405,
        "otherCurrentAssets": 26,
        "otherCurrentliabilities": 15,
        "otherEquity": 0,
        "otherLiabilities": 32,
        "otherLongTermAssets": 538,
        "otherReceivables": 0,
        "period": "2016-03-31",
        "propertyPlantEquipment": 150,
        "retainedEarnings": 3583,
        "sharesOutstanding": 371,
        "shortTermDebt": 495,
        "tangibleBookValueperShare": 16.6065,
        "totalAssets": 11300,
        "totalDebt": 3663,
        "totalEquity": 6248,
        "totalLiabilities": 5052,
        "totalReceivables": 25,
        "treasuryStock": -134
      },
      {
        "accountsPayable": 449,
        "accountsReceivables": 30,
        "accruedLiability": 841,
        "additionalPaidInCapital": 2770,
        "cashEquivalents": 1269,
        "cashShortTermInvestments": 1269,
        "commonStock": 4,
        "currentAssets": 9419,
        "currentLiabilities": 1752,
        "goodwill": 87,
        "inventory": 8088,
        "liabilitiesShareholdersEquity": 11180,
        "longTermDebt": 3337,
        "minorityInterest": 1,
        "netDebt": 2465,
        "noteReceivableLongTerm": 652,
        "otherAssets": 409,
        "otherCurrentAssets": 32,
        "otherCurrentliabilities": 65,
        "otherEquity": 3,
        "otherLiabilities": 30,
        "otherLongTermAssets": 552,
        "otherReceivables": 0,
        "period": "2015-12-31",
        "propertyPlantEquipment": 148,
        "retainedEarnings": 3418,
        "sharesOutstanding": 370,
        "shortTermDebt": 397,
        "tangibleBookValueperShare": 16.1405,
        "totalAssets": 11180,
        "totalDebt": 3734,
        "totalEquity": 6059,
        "totalLiabilities": 5120,
        "totalReceivables": 30,
        "treasuryStock": -134
      },
      {
        "accountsPayable": 515,
        "accountsReceivables": 49,
        "accruedLiability": 857,
        "additionalPaidInCapital": 2734,
        "cashEquivalents": 1384,
        "cashShortTermInvestments": 1384,
        "commonStock": 4,
        "currentAssets": 9281,
        "currentLiabilities": 1886,
        "goodwill": 87,
        "inventory": 7807,
        "liabilitiesShareholdersEquity": 11151,
        "longTermDebt": 3334,
        "minorityInterest": 1,
        "netDebt": 2428,
        "noteReceivableLongTerm": 758,
        "otherAssets": 401,
        "otherCurrentAssets": 41,
        "otherCurrentliabilities": 36,
        "otherEquity": 1,
        "otherLiabilities": 36,
        "otherLongTermAssets": 568,
        "otherReceivables": 0,
        "period": "2015-09-30",
        "propertyPlantEquipment": 144,
        "retainedEarnings": 3290,
        "sharesOutstanding": 369,
        "shortTermDebt": 478,
        "tangibleBookValueperShare": 15.7371,
        "totalAssets": 11151,
        "totalDebt": 3812,
        "totalEquity": 5894,
        "totalLiabilities": 5257,
        "totalReceivables": 49,
        "treasuryStock": -134
      }
    ],
    "symbol": "DHI"
  }
}