{
  "symbol": "HRL",
  "statement": "bs",
  "frequency": "quarterly",
  "timestamp": "2025-09-19T14:01:39.215403",
  "data": {
    "financials": [
      {
        "accountsPayable": 707.753,
        "accountsReceivables": 764.338,
        "accruedLiability": 602.585,
        "accumulatedDepreciation": -2638.553,
        "additionalPaidInCapital": 617.598,
        "cashEquivalents": 599.189,
        "cashShortTermInvestments": 630.669,
        "commonStock": 8.057,
        "currentAssets": 3322.49,
        "currentLiabilities": 1345.531,
        "currentPortionLongTermDebt": 6.74,
        "deferredIncomeTax": 595.066,
        "goodwill": 4923.218,
        "intangiblesAssets": 1721.487,
        "inventory": 1821.86,
        "liabilitiesShareholdersEquity": 13496.726,
        "longTermDebt": 2850.165,
        "longTermInvestments": 698.632,
        "minorityInterest": 9.824,
        "netDebt": 2226.236,
        "otherAssets": 4923.218,
        "otherCurrentAssets": 55.064,
        "otherCurrentliabilities": 28.453,
        "otherEquity": -275.934,
        "otherLiabilities": 612.872,
        "otherLongTermAssets": 618.19,
        "otherReceivables": 50.559,
        "period": "2025-07-27",
        "propertyPlantEquipment": 2212.709,
        "retainedEarnings": 7732.618,
        "sharesOutstanding": 549.9984,
        "shortTermDebt": 0,
        "shortTermInvestments": 31.48,
        "tangibleBookValueperShare": 2.6156,
        "totalAssets": 13496.726,
        "totalDebt": 2856.905,
        "totalEquity": 8083.268,
        "totalLiabilities": 5413.458,
        "totalReceivables": 814.897,
        "unrealizedProfitLossSecurity": 0.929
      },
      {
        "accountsPayable": 716.892,
        "accountsReceivables": 743.981,
        "accruedLiability": 592.398,
        "accumulatedDepreciation": -2590.282,
        "additionalPaidInCapital": 614.189,
        "cashEquivalents": 669.688,
        "cashShortTermInvestments": 698.981,
        "commonStock": 8.056,
        "currentAssets": 3282.069,
        "currentLiabilities": 1327.664,
        "currentPortionLongTermDebt": 7.249,
        "deferredIncomeTax": 594.504,
        "goodwill": 4920.635,
        "intangiblesAssets": 1724.81,
        "inventory": 1729.237,
        "liabilitiesShareholdersEquity": 13421.808,
        "longTermDebt": 2850.697,
        "longTermInvestments": 682.81,
        "minorityInterest": 9.604,
        "netDebt": 2158.965,
        "otherAssets": 4920.635,
        "otherCurrentAssets": 59.341,
        "otherCurrentliabilities": 11.125,
        "otherEquity": -293.773,
        "otherLiabilities": 607.002,
        "otherLongTermAssets": 619.641,
        "otherReceivables": 50.529,
        "period": "2025-04-27",
        "propertyPlantEquipment": 2191.843,
        "retainedEarnings": 7708.693,
        "sharesOutstanding": 549.8876,
        "shortTermDebt": 0,
        "shortTermInvestments": 29.293,
        "tangibleBookValueperShare": 2.5221,
        "totalAssets": 13421.808,
        "totalDebt": 2857.946,
        "totalEquity": 8032.337,
        "totalLiabilities": 5389.471,
        "totalReceivables": 794.51,
        "unrealizedProfitLossSecurity": -4.828
      },
      {
        "accountsPayable": 709.19,
        "accountsReceivables": 767.804,
        "accruedLiability": 606.433,
        "accumulatedDepreciation": -2549.414,
        "additionalPaidInCapital": 602.887,
        "cashEquivalents": 840.398,
        "cashShortTermInvestments": 866.414,
        "commonStock": 8.054,
        "currentAssets": 3266.068,
        "currentLiabilities": 1331.81,
        "currentPortionLongTermDebt": 7.187,
        "deferredIncomeTax": 594.788,
        "goodwill": 4916.874,
        "intangiblesAssets": 1727.655,
        "inventory": 1516.716,
        "liabilitiesShareholdersEquity": 13403.483,
        "longTermDebt": 2850.206,
        "longTermInvestments": 710.433,
        "minorityInterest": 10.101,
        "netDebt": 1990.979,
        "otherAssets": 4916.874,
        "otherCurrentAssets": 64.387,
        "otherCurrentliabilities": 9,
        "otherEquity": -264.533,
        "otherLiabilities": 588.237,
        "otherLongTermAssets": 607.664,
        "otherReceivables": 50.747,
        "period": "2025-01-26",
        "propertyPlantEquipment": 2174.789,
        "retainedEarnings": 7688.663,
        "sharesOutstanding": 549.7855,
        "shortTermDebt": 0,
        "shortTermInvestments": 26.016,
        "tangibleBookValueperShare": 2.517,
        "totalAssets": 13403.483,
        "totalDebt": 2857.393,
        "totalEquity": 8028.341,
        "totalLiabilities": 5375.142,
        "totalReceivables": 818.551,
        "unrealizedProfitLossSecurity": -6.73
      },
      {
        "accountsPayable": 735.604,
        "accountsReceivables": 817.908,
        "accruedLiability": 633.967,
        "accumulatedDepreciation": -2517.734,
        "additionalPaidInCapital": 571.178,
        "cashEquivalents": 741.881,
        "cashShortTermInvestments": 766.623,
        "commonStock": 8.037,
        "currentAssets": 3246.476,
        "currentLiabilities": 1399.299,
        "currentPortionLongTermDebt": 7.813,
        "deferredIncomeTax": 589.366,
        "goodwill": 4923.487,
        "intangiblesAssets": 1732.705,
        "inventory": 1576.3,
        "liabilitiesShareholdersEquity": 13434.729,
        "longTermDebt": 2850.944,
        "longTermInvestments": 719.481,
        "minorityInterest": 10.59,
        "netDebt": 2092.134,
        "otherAssets": 4923.487,
        "otherCurrentAssets": 35.265,
        "otherCurrentliabilities": 21.915,
        "otherEquity": -256.127,
        "otherLiabilities": 591.109,
        "otherLongTermAssets": 617.852,
        "otherReceivables": 50.38,
        "period": "2024-10-27",
        "propertyPlantEquipment": 2194.728,
        "retainedEarnings": 7677.537,
        "sharesOutstanding": 548.6053,
        "shortTermDebt": 0,
        "shortTermInvestments": 24.742,
        "tangibleBookValueperShare": 2.4375,
        "totalAssets": 13434.729,
        "totalDebt": 2858.757,
        "totalEquity": 7993.421,
        "totalLiabilities": 5441.308,
        "totalReceivables": 868.288,
        "unrealizedProfitLossSecurity": -7.204
      },
      {
        "accountsPayable": 675.167,
        "accountsReceivables": 727.054,
        "accruedLiability": 607.834,
        "accumulatedDepreciation": -2467.997,
        "additionalPaidInCapital": 560.849,
        "cashEquivalents": 537.476,
        "cashShortTermInvestments": 561.93,
        "commonStock": 8.033,
        "currentAssets": 2997.446,
        "currentLiabilities": 1309.746,
        "currentPortionLongTermDebt": 8.232,
        "deferredIncomeTax": 499.098,
        "goodwill": 4923.731,
        "intangiblesAssets": 1743.615,
        "inventory": 1649.649,
        "liabilitiesShareholdersEquity": 13113.781,
        "longTermDebt": 2851.621,
        "longTermInvestments": 680.386,
        "minorityInterest": 10.106,
        "netDebt": 2297.923,
        "otherAssets": 4923.731,
        "otherCurrentAssets": 58.813,
        "otherCurrentliabilities": 18.513,
        "otherEquity": -310.889,
        "otherLiabilities": 576.091,
        "otherLongTermAssets": 600.072,
        "otherReceivables": 0,
        "period": "2024-07-28",
        "propertyPlantEquipment": 2168.531,
        "retainedEarnings": 7612.61,
        "sharesOutstanding": 548.3286,
        "shortTermDebt": 0,
        "shortTermInvestments": 24.454,
        "tangibleBookValueperShare": 2.1881,
        "totalAssets": 13113.781,
        "totalDebt": 2859.853,
        "totalEquity": 7867.119,
        "totalLiabilities": 5246.662,
        "totalReceivables": 727.054,
        "unrealizedProfitLossSecurity": -3.484
      },
      {
        "accountsPayable": 691.498,
        "accountsReceivables": 731.984,
        "accruedLiability": 602.448,
        "accumulatedDepreciation": -2424.237,
        "additionalPaidInCapital": 549.13,
        "cashEquivalents": 1486.368,
        "cashShortTermInvestments": 1509.442,
        "commonStock": 8.028,
        "currentAssets": 3976.519,
        "currentLiabilities": 2304.811,
        "currentPortionLongTermDebt": 957.292,
        "deferredIncomeTax": 504.907,
        "goodwill": 4929.034,
        "intangiblesAssets": 1748.778,
        "inventory": 1673.5,
        "liabilitiesShareholdersEquity": 14135.373,
        "longTermDebt": 2852.604,
        "longTermInvestments": 710.029,
        "minorityInterest": 10.462,
        "netDebt": 2300.454,
        "otherAssets": 4929.034,
        "otherCurrentAssets": 61.593,
        "otherCurrentliabilities": 53.573,
        "otherEquity": -265.611,
        "otherLiabilities": 576.599,
        "otherLongTermAssets": 607.889,
        "otherReceivables": 0,
        "period": "2024-04-28",
        "propertyPlantEquipment": 2163.124,
        "retainedEarnings": 7591.157,
        "sharesOutstanding": 548.0296,
        "shortTermDebt": 0,
        "shortTermInvestments": 23.074,
        "tangibleBookValueperShare": 2.2046,
        "totalAssets": 14135.373,
        "totalDebt": 3809.896,
        "totalEquity": 7885.99,
        "totalLiabilities": 6249.383,
        "totalReceivables": 731.984,
        "unrealizedProfitLossSecurity": 3.286
      },
      {
        "accountsPayable": 744.116,
        "accountsReceivables": 751.048,
        "accruedLiability": 477.099,
        "accumulatedDepreciation": -2380.631,
        "additionalPaidInCapital": 529.715,
        "cashEquivalents": 963.212,
        "cashShortTermInvestments": 981.924,
        "commonStock": 8.021,
        "currentAssets": 3367.164,
        "currentLiabilities": 2260.779,
        "currentPortionLongTermDebt": 954.031,
        "deferredIncomeTax": 500.581,
        "goodwill": 4931.257,
        "intangiblesAssets": 1753.156,
        "inventory": 1578.191,
        "liabilitiesShareholdersEquity": 13512.983,
        "longTermDebt": 2357.176,
        "longTermInvestments": 728.146,
        "minorityInterest": 4.455,
        "netDebt": 2329.283,
        "otherAssets": 4931.257,
        "otherCurrentAssets": 56.001,
        "otherCurrentliabilities": 85.533,
        "otherEquity": -260.512,
        "otherLiabilities": 545.881,
        "otherLongTermAssets": 577.736,
        "otherReceivables": 0,
        "period": "2024-01-28",
        "propertyPlantEquipment": 2155.524,
        "retainedEarnings": 7557.157,
        "sharesOutstanding": 547.596,
        "shortTermDebt": 0,
        "shortTermInvestments": 18.712,
        "tangibleBookValueperShare": 2.1178,
        "totalAssets": 13512.983,
        "totalDebt": 3311.207,
        "totalEquity": 7844.111,
        "totalLiabilities": 5668.872,
        "totalReceivables": 751.048,
        "unrealizedProfitLossSecurity": 9.73
      },
      {
        "accountsPayable": 771.397,
        "accountsReceivables": 817.391,
        "accruedLiability": 574.639,
        "accumulatedDepreciation": -2344.557,
        "additionalPaidInCapital": 506.179,
        "cashEquivalents": 736.532,
        "cashShortTermInvestments": 753.196,
        "commonStock": 8.007,
        "currentAssets": 3297.249,
        "currentLiabilities": 2311.776,
        "currentPortionLongTermDebt": 950.529,
        "deferredIncomeTax": 498.106,
        "goodwill": 4928.464,
        "intangiblesAssets": 1757.171,
        "inventory": 1680.406,
        "liabilitiesShareholdersEquity": 13448.772,
        "longTermDebt": 2358.719,
        "longTermInvestments": 725.121,
        "minorityInterest": 4.1,
        "netDebt": 2556.052,
        "otherAssets": 4928.464,
        "otherCurrentAssets": 39.014,
        "otherCurrentliabilities": 15.211,
        "otherEquity": -279.1,
        "otherLiabilities": 541.186,
        "otherLongTermAssets": 574.949,
        "otherReceivables": 7.242,
        "period": "2023-10-29",
        "propertyPlantEquipment": 2165.818,
        "retainedEarnings": 7492.952,
        "sharesOutstanding": 546.5994,
        "shortTermDebt": 0,
        "shortTermInvestments": 16.664,
        "tangibleBookValueperShare": 1.9196,
        "totalAssets": 13448.772,
        "totalDebt": 3309.248,
        "totalEquity": 7734.885,
        "totalLiabilities": 5713.887,
        "totalReceivables": 824.633,
        "unrealizedProfitLossSecurity": 6.847
      },
      {
        "accountsPayable": 703,
        "accountsReceivables": 786,
        "accruedLiability": 621,
        "accumulatedDepreciation": -2301,
        "additionalPaidInCapital": 499,
        "cashEquivalents": 669,
        "cashShortTermInvestments": 687,
        "commonStock": 8,
        "currentAssets": 3255,
        "currentLiabilities": 2321,
        "currentPortionLongTermDebt": 947,
        "deferredIncomeTax": 468,
        "goodwill": 4932,
        "intangiblesAssets": 1791,
        "inventory": 1738,
        "liabilitiesShareholdersEquity": 13427,
        "longTermDebt": 2360,
        "longTermInvestments": 743,
        "minorityInterest": 5,
        "netDebt": 2620,
        "otherAssets": 4932,
        "otherCurrentAssets": 37,
        "otherCurrentliabilities": 50,
        "otherEquity": -252,
        "otherLiabilities": 560,
        "otherLongTermAssets": 575,
        "otherReceivables": 8,
        "period": "2023-07-30",
        "propertyPlantEquipment": 2131,
        "retainedEarnings": 7448,
        "sharesOutstanding": 546,
        "shortTermDebt": 0,
        "shortTermInvestments": 17,
        "tangibleBookValueperShare": 1.8132,
        "totalAssets": 13427,
        "totalDebt": 3307,
        "totalEquity": 7713,
        "totalLiabilities": 5713,
        "totalReceivables": 794,
        "unrealizedProfitLossSecurity": 10
      },
      {
        "accountsPayable": 750,
        "accountsReceivables": 762,
        "accruedLiability": 499,
        "accumulatedDepreciation": -2257,
        "additionalPaidInCapital": 488,
        "cashEquivalents": 580,
        "cashShortTermInvestments": 598,
        "commonStock": 8,
        "currentAssets": 3163,
        "currentLiabilities": 1305,
        "currentPortionLongTermDebt": 9,
        "deferredIncomeTax": 466,
        "goodwill": 4930,
        "intangiblesAssets": 1795,
        "inventory": 1746,
        "liabilitiesShareholdersEquity": 13316,
        "longTermDebt": 3294,
        "longTermInvestments": 742,
        "minorityInterest": 5,
        "netDebt": 2705,
        "otherAssets": 4930,
        "otherCurrentAssets": 50,
        "otherCurrentliabilities": 47,
        "otherEquity": -246,
        "otherLiabilities": 558,
        "otherLongTermAssets": 567,
        "otherReceivables": 7,
        "period": "2023-04-30",
        "propertyPlantEquipment": 2119,
        "retainedEarnings": 7435,
        "sharesOutstanding": 546,
        "shortTermDebt": 0,
        "shortTermInvestments": 18,
        "tangibleBookValueperShare": 1.7619,
        "totalAssets": 13316,
        "totalDebt": 3303,
        "totalEquity": 7687,
        "totalLiabilities": 5629,
        "totalReceivables": 769,
        "unrealizedProfitLossSecurity": 1
      },
      {
        "accountsPayable": 765,
        "accountsReceivables": 787,
        "accruedLiability": 505,
        "accumulatedDepreciation": -2224,
        "additionalPaidInCapital": 477,
        "cashEquivalents": 600,
        "cashShortTermInvestments": 618,
        "commonStock": 8,
        "currentAssets": 3195,
        "currentLiabilities": 1373,
        "currentPortionLongTermDebt": 9,
        "deferredIncomeTax": 471,
        "goodwill": 4928,
        "intangiblesAssets": 1799,
        "inventory": 1730,
        "liabilitiesShareholdersEquity": 13283,
        "longTermDebt": 3293,
        "longTermInvestments": 702,
        "minorityInterest": 5,
        "netDebt": 2683,
        "otherAssets": 4928,
        "otherCurrentAssets": 53,
        "otherCurrentliabilities": 95,
        "otherEquity": -252,
        "otherLiabilities": 527,
        "otherLongTermAssets": 535,
        "otherReceivables": 7,
        "period": "2023-01-29",
        "propertyPlantEquipment": 2124,
        "retainedEarnings": 7381,
        "sharesOutstanding": 546,
        "shortTermDebt": 0,
        "shortTermInvestments": 18,
        "tangibleBookValueperShare": 1.6245,
        "totalAssets": 13283,
        "totalDebt": 3301,
        "totalEquity": 7614,
        "totalLiabilities": 5669,
        "totalReceivables": 794
      },
      {
        "accountsPayable": 817,
        "accountsReceivables": 868,
        "accruedLiability": 615,
        "accumulatedDepreciation": -2184,
        "additionalPaidInCapital": 469,
        "cashEquivalents": 982,
        "cashShortTermInvestments": 998,
        "commonStock": 8,
        "currentAssets": 3637,
        "currentLiabilities": 1473,
        "currentPortionLongTermDebt": 9,
        "deferredIncomeTax": 475,
        "goodwill": 4926,
        "intangiblesAssets": 1803,
        "inventory": 1716,
        "liabilitiesShareholdersEquity": 13307,
        "longTermDebt": 3291,
        "longTermInvestments": 271,
        "minorityInterest": 5,
        "netDebt": 2301,
        "otherAssets": 4926,
        "otherCurrentAssets": 48,
        "otherCurrentliabilities": 33,
        "otherEquity": -256,
        "otherLiabilities": 528,
        "otherLongTermAssets": 529,
        "otherReceivables": 7,
        "period": "2022-10-30",
        "propertyPlantEquipment": 2141,
        "retainedEarnings": 7313,
        "sharesOutstanding": 546,
        "shortTermDebt": 0,
        "shortTermInvestments": 16,
        "tangibleBookValueperShare": 1.4762,
        "totalAssets": 13307,
        "totalDebt": 3299,
        "totalEquity": 7535,
        "totalLiabilities": 5772,
        "totalReceivables": 875
      },
      {
        "accountsPayable": 799,
        "accountsReceivables": 803,
        "accruedLiability": 548,
        "accumulatedDepreciation": -2142,
        "additionalPaidInCapital": 459,
        "cashEquivalents": 850,
        "cashShortTermInvestments": 869,
        "commonStock": 8,
        "currentAssets": 3403,
        "currentLiabilities": 1420,
        "currentPortionLongTermDebt": 9,
        "deferredIncomeTax": 354,
        "goodwill": 4929,
        "intangiblesAssets": 1808,
        "inventory": 1679,
        "liabilitiesShareholdersEquity": 13140,
        "longTermDebt": 3294,
        "longTermInvestments": 278,
        "minorityInterest": 5,
        "netDebt": 2434,
        "otherAssets": 4929,
        "otherCurrentAssets": 45,
        "otherCurrentliabilities": 64,
        "otherEquity": -283,
        "otherLiabilities": 705,
        "otherLongTermAssets": 604,
        "otherReceivables": 8,
        "period": "2022-07-31",
        "propertyPlantEquipment": 2118,
        "retainedEarnings": 7177,
        "sharesOutstanding": 546,
        "shortTermDebt": 0,
        "shortTermInvestments": 18,
        "tangibleBookValueperShare": 1.1447,
        "totalAssets": 13140,
        "totalDebt": 3303,
        "totalEquity": 7362,
        "totalLiabilities": 5779,
        "totalReceivables": 811
      },
      {
        "accountsPayable": 827,
        "accountsReceivables": 795,
        "accruedLiability": 553,
        "accumulatedDepreciation": -2104,
        "additionalPaidInCapital": 452,
        "cashEquivalents": 862,
        "cashShortTermInvestments": 885,
        "commonStock": 8,
        "currentAssets": 3374,
        "currentLiabilities": 1481,
        "currentPortionLongTermDebt": 8,
        "deferredIncomeTax": 292,
        "goodwill": 4936,
        "intangiblesAssets": 1815,
        "inventory": 1597,
        "liabilitiesShareholdersEquity": 13122,
        "longTermDebt": 3294,
        "longTermInvestments": 276,
        "minorityInterest": 6,
        "netDebt": 2417,
        "otherAssets": 4936,
        "otherCurrentAssets": 88,
        "otherCurrentliabilities": 93,
        "otherEquity": -221,
        "otherLiabilities": 710,
        "otherLongTermAssets": 599,
        "otherReceivables": 8,
        "period": "2022-05-01",
        "propertyPlantEquipment": 2124,
        "retainedEarnings": 7101,
        "sharesOutstanding": 546,
        "shortTermDebt": 0,
        "shortTermInvestments": 23,
        "tangibleBookValueperShare": 1.0769,
        "totalAssets": 13122,
        "totalDebt": 3302,
        "totalEquity": 7339,
        "totalLiabilities": 5783,
        "totalReceivables": 803
      },
      {
        "accountsPayable": 799,
        "accountsReceivables": 813,
        "accruedLiability": 518,
        "accumulatedDepreciation": -2069,
        "additionalPaidInCapital": 378,
        "cashEquivalents": 824,
        "cashShortTermInvestments": 847,
        "commonStock": 8,
        "currentAssets": 3093,
        "currentLiabilities": 1415,
        "currentPortionLongTermDebt": 9,
        "deferredIncomeTax": 282,
        "goodwill": 4928,
        "intangiblesAssets": 1817,
        "inventory": 1386,
        "liabilitiesShareholdersEquity": 12827,
        "longTermDebt": 3309,
        "longTermInvestments": 286,
        "minorityInterest": 6,
        "netDebt": 2471,
        "otherAssets": 4928,
        "otherCurrentAssets": 41,
        "otherCurrentliabilities": 89,
        "otherEquity": -266,
        "otherLiabilities": 715,
        "otherLongTermAssets": 600,
        "otherReceivables": 7,
        "period": "2022-01-30",
        "propertyPlantEquipment": 2102,
        "retainedEarnings": 6980,
        "sharesOutstanding": 543,
        "shortTermDebt": 0,
        "shortTermInvestments": 22,
        "tangibleBookValueperShare": 0.6556,
        "totalAssets": 12827,
        "totalDebt": 3318,
        "totalEquity": 7101,
        "totalLiabilities": 5726,
        "totalReceivables": 820
      },
      {
        "accountsPayable": 793,
        "accountsReceivables": 896,
        "accruedLiability": 590,
        "accumulatedDepreciation": -2027,
        "additionalPaidInCapital": 360,
        "cashEquivalents": 614,
        "cashShortTermInvestments": 635,
        "commonStock": 8,
        "currentAssets": 2948,
        "currentLiabilities": 1416,
        "currentPortionLongTermDebt": 9,
        "deferredIncomeTax": 278,
        "goodwill": 4929,
        "intangiblesAssets": 1822,
        "inventory": 1369,
        "liabilitiesShareholdersEquity": 12696,
        "longTermDebt": 3315,
        "longTermInvestments": 299,
        "minorityInterest": 5,
        "netDebt": 2689,
        "otherAssets": 4929,
        "otherCurrentAssets": 40,
        "otherCurrentliabilities": 24,
        "otherEquity": -277,
        "otherLiabilities": 709,
        "otherLongTermAssets": 517,
        "otherReceivables": 8,
        "period": "2021-10-31",
        "propertyPlantEquipment": 2181,
        "retainedEarnings": 6882,
        "sharesOutstanding": 542,
        "shortTermDebt": 0,
        "shortTermInvestments": 21,
        "tangibleBookValueperShare": 0.4096,
        "totalAssets": 12696,
        "totalDebt": 3324,
        "totalEquity": 6973,
        "totalLiabilities": 5723,
        "totalReceivables": 904
      },
      {
        "accountsPayable": 654,
        "accountsReceivables": 896,
        "accruedLiability": 571,
        "accumulatedDepreciation": -1984,
        "additionalPaidInCapital": 354,
        "cashEquivalents": 291,
        "cashShortTermInvestments": 310,
        "commonStock": 8,
        "currentAssets": 2689,
        "currentLiabilities": 1251,
        "currentPortionLongTermDebt": 9,
        "deferredIncomeTax": 237,
        "goodwill": 4907,
        "intangiblesAssets": 1864,
        "inventory": 1427,
        "liabilitiesShareholdersEquity": 12332,
        "longTermDebt": 3316,
        "longTermInvestments": 304,
        "minorityInterest": 5,
        "netDebt": 3015,
        "otherAssets": 4907,
        "otherCurrentAssets": 40,
        "otherCurrentliabilities": 17,
        "otherEquity": -318,
        "otherLiabilities": 734,
        "otherLongTermAssets": 501,
        "otherReceivables": 16,
        "period": "2021-07-25",
        "propertyPlantEquipment": 2067,
        "retainedEarnings": 6744,
        "sharesOutstanding": 543,
        "shortTermDebt": 0,
        "shortTermInvestments": 18,
        "tangibleBookValueperShare": 0.0313,
        "totalAssets": 12332,
        "totalDebt": 3325,
        "totalEquity": 6788,
        "totalLiabilities": 5544,
        "totalReceivables": 912
      },
      {
        "accountsPayable": 577,
        "accountsReceivables": 722,
        "accruedLiability": 560,
        "accumulatedDepreciation": -1941,
        "additionalPaidInCapital": 319,
        "cashEquivalents": 1485,
        "cashShortTermInvestments": 1502,
        "commonStock": 8,
        "currentAssets": 3514,
        "currentLiabilities": 1175,
        "currentPortionLongTermDebt": 9,
        "deferredIncomeTax": 237,
        "goodwill": 2614,
        "intangiblesAssets": 1068,
        "inventory": 1229,
        "liabilitiesShareholdersEquity": 9889,
        "longTermDebt": 1040,
        "longTermInvestments": 309,
        "minorityInterest": 5,
        "netDebt": -452,
        "otherAssets": 2614,
        "otherCurrentAssets": 52,
        "otherCurrentliabilities": 29,
        "otherEquity": -326,
        "otherLiabilities": 730,
        "otherLongTermAssets": 486,
        "otherReceivables": 9,
        "period": "2021-04-25",
        "propertyPlantEquipment": 1897,
        "retainedEarnings": 6699,
        "sharesOutstanding": 540,
        "shortTermDebt": 0,
        "shortTermInvestments": 18,
        "tangibleBookValueperShare": 5.5907,
        "totalAssets": 9889,
        "totalDebt": 1050,
        "totalEquity": 6701,
        "totalLiabilities": 3188,
        "totalReceivables": 731
      },
      {
        "accountsPayable": 559,
        "accountsReceivables": 707,
        "accruedLiability": 554,
        "accumulatedDepreciation": -1903,
        "additionalPaidInCapital": 299,
        "cashEquivalents": 1752,
        "cashShortTermInvestments": 1769,
        "commonStock": 8,
        "currentAssets": 3602,
        "currentLiabilities": 1417,
        "currentPortionLongTermDebt": 259,
        "deferredIncomeTax": 224,
        "goodwill": 2618,
        "intangiblesAssets": 1073,
        "inventory": 1087,
        "liabilitiesShareholdersEquity": 9958,
        "longTermDebt": 1043,
        "longTermInvestments": 305,
        "minorityInterest": 5,
        "netDebt": -467,
        "otherAssets": 2618,
        "otherCurrentAssets": 30,
        "otherCurrentliabilities": 46,
        "otherEquity": -361,
        "otherLiabilities": 717,
        "otherLongTermAssets": 462,
        "otherReceivables": 9,
        "period": "2021-01-24",
        "propertyPlantEquipment": 1898,
        "retainedEarnings": 6605,
        "sharesOutstanding": 540,
        "shortTermDebt": 0,
        "shortTermInvestments": 18,
        "tangibleBookValueperShare": 5.2963,
        "totalAssets": 9958,
        "totalDebt": 1302,
        "totalEquity": 6551,
        "totalLiabilities": 3407,
        "totalReceivables": 716
      },
      {
        "accountsPayable": 645,
        "accountsReceivables": 702,
        "accruedLiability": 578,
        "accumulatedDepreciation": -1869,
        "additionalPaidInCapital": 290,
        "cashEquivalents": 1714,
        "cashShortTermInvestments": 1732,
        "commonStock": 8,
        "currentAssets": 3579,
        "currentLiabilities": 1504,
        "currentPortionLongTermDebt": 259,
        "deferredIncomeTax": 219,
        "goodwill": 2613,
        "intangiblesAssets": 1076,
        "inventory": 1073,
        "liabilitiesShareholdersEquity": 9908,
        "longTermDebt": 1045,
        "longTermInvestments": 308,
        "minorityInterest": 5,
        "netDebt": -428,
        "otherAssets": 2613,
        "otherCurrentAssets": 30,
        "otherCurrentliabilities": 22,
        "otherEquity": -395,
        "otherLiabilities": 710,
        "otherLongTermAssets": 380,
        "otherReceivables": 42,
        "period": "2020-10-25",
        "propertyPlantEquipment": 1951,
        "retainedEarnings": 6523,
        "sharesOutstanding": 540,
        "shortTermDebt": 0,
        "shortTermInvestments": 17,
        "tangibleBookValueperShare": 5.0685,
        "totalAssets": 9908,
        "totalDebt": 1304,
        "totalEquity": 6426,
        "totalLiabilities": 3483,
        "totalReceivables": 744
      },
      {
        "accountsPayable": 538,
        "accountsReceivables": 649,
        "accruedLiability": 581,
        "accumulatedDepreciation": -1837,
        "additionalPaidInCapital": 277,
        "cashEquivalents": 1729,
        "cashShortTermInvestments": 1747,
        "commonStock": 8,
        "currentAssets": 3410,
        "currentLiabilities": 1427,
        "currentPortionLongTermDebt": 259,
        "deferredIncomeTax": 170,
        "goodwill": 2616,
        "intangiblesAssets": 1081,
        "inventory": 982,
        "liabilitiesShareholdersEquity": 9600,
        "longTermDebt": 1047,
        "longTermInvestments": 299,
        "minorityInterest": 4,
        "netDebt": -441,
        "otherAssets": 2616,
        "otherCurrentAssets": 31,
        "otherCurrentliabilities": 50,
        "otherEquity": -432,
        "otherLiabilities": 685,
        "otherLongTermAssets": 340,
        "otherReceivables": 1,
        "period": "2020-07-26",
        "propertyPlantEquipment": 1856,
        "retainedEarnings": 6415,
        "sharesOutstanding": 539,
        "shortTermDebt": 0,
        "shortTermInvestments": 18,
        "tangibleBookValueperShare": 4.7681,
        "totalAssets": 9600,
        "totalDebt": 1306,
        "totalEquity": 6267,
        "totalLiabilities": 3333,
        "totalReceivables": 650
      },
      {
        "accountsPayable": 496,
        "accountsReceivables": 536,
        "accruedLiability": 509,
        "accumulatedDepreciation": -1799,
        "additionalPaidInCapital": 265,
        "cashEquivalents": 606,
        "cashShortTermInvestments": 623,
        "commonStock": 8,
        "currentAssets": 2249,
        "currentLiabilities": 1325,
        "currentPortionLongTermDebt": 258,
        "deferredIncomeTax": 165,
        "goodwill": 2683,
        "intangiblesAssets": 1024,
        "inventory": 1049,
        "liabilitiesShareholdersEquity": 8395,
        "longTermDebt": 57,
        "longTermInvestments": 303,
        "minorityInterest": 4,
        "netDebt": -308,
        "otherAssets": 2683,
        "otherCurrentAssets": 40,
        "otherCurrentliabilities": 60,
        "otherEquity": -448,
        "otherLiabilities": 682,
        "otherLongTermAssets": 327,
        "otherReceivables": 0,
        "period": "2020-04-26",
        "propertyPlantEquipment": 1809,
        "retainedEarnings": 6337,
        "sharesOutstanding": 539,
        "shortTermDebt": 0,
        "shortTermInvestments": 17,
        "tangibleBookValueperShare": 4.5547,
        "totalAssets": 8395,
        "totalDebt": 315,
        "totalEquity": 6162,
        "totalLiabilities": 2233,
        "totalReceivables": 536
      },
      {
        "accountsPayable": 488,
        "accountsReceivables": 562,
        "accruedLiability": 494,
        "accumulatedDepreciation": -1763,
        "additionalPaidInCapital": 231,
        "cashEquivalents": 724,
        "cashShortTermInvestments": 739,
        "commonStock": 8,
        "currentAssets": 2395,
        "currentLiabilities": 1023,
        "currentPortionLongTermDebt": 8,
        "deferredIncomeTax": 176,
        "goodwill": 2484,
        "intangiblesAssets": 1032,
        "inventory": 1057,
        "liabilitiesShareholdersEquity": 8290,
        "longTermDebt": 309,
        "longTermInvestments": 291,
        "minorityInterest": 4,
        "netDebt": -422,
        "otherAssets": 2484,
        "otherCurrentAssets": 36,
        "otherCurrentliabilities": 33,
        "otherEquity": -393,
        "otherLiabilities": 686,
        "otherLongTermAssets": 333,
        "otherReceivables": 1,
        "period": "2020-01-26",
        "propertyPlantEquipment": 1755,
        "retainedEarnings": 6247,
        "sharesOutstanding": 537,
        "shortTermDebt": 0,
        "shortTermInvestments": 15,
        "tangibleBookValueperShare": 4.797,
        "totalAssets": 8290,
        "totalDebt": 317,
        "totalEquity": 6092,
        "totalLiabilities": 2198,
        "totalReceivables": 563
      },
      {
        "accountsPayable": 587,
        "accountsReceivables": 574,
        "accruedLiability": 509,
        "accumulatedDepreciation": -1726,
        "additionalPaidInCapital": 185,
        "cashEquivalents": 673,
        "cashShortTermInvestments": 688,
        "commonStock": 8,
        "currentAssets": 2361,
        "currentLiabilities": 1105,
        "deferredIncomeTax": 177,
        "goodwill": 2482,
        "intangiblesAssets": 1034,
        "inventory": 1042,
        "liabilitiesShareholdersEquity": 8109,
        "longTermDebt": 250,
        "longTermInvestments": 289,
        "minorityInterest": 4,
        "netDebt": -438,
        "otherAssets": 2482,
        "otherCurrentAssets": 37,
        "otherCurrentliabilities": 9,
        "otherEquity": -400,
        "otherLiabilities": 652,
        "otherLongTermAssets": 314,
        "otherReceivables": 20,
        "period": "2019-10-27",
        "propertyPlantEquipment": 1629,
        "retainedEarnings": 6128,
        "sharesOutstanding": 534,
        "shortTermDebt": 0,
        "shortTermInvestments": 15,
        "tangibleBookValueperShare": 4.5037,
        "totalAssets": 8109,
        "totalDebt": 250,
        "totalEquity": 5921,
        "totalLiabilities": 2188,
        "totalReceivables": 594
      },
      {
        "accountsPayable": 512,
        "accountsReceivables": 529,
        "accruedLiability": 525,
        "accumulatedDepreciation": -1699,
        "additionalPaidInCapital": 170,
        "cashEquivalents": 560,
        "cashShortTermInvestments": 574,
        "commonStock": 8,
        "currentAssets": 2246,
        "currentLiabilities": 1073,
        "deferredIncomeTax": 145,
        "goodwill": 2487,
        "intangiblesAssets": 1038,
        "inventory": 1109,
        "liabilitiesShareholdersEquity": 7955,
        "longTermDebt": 250,
        "longTermInvestments": 279,
        "minorityInterest": 4,
        "netDebt": -324,
        "otherAssets": 2487,
        "otherCurrentAssets": 34,
        "otherCurrentliabilities": 36,
        "otherEquity": -275,
        "otherLiabilities": 595,
        "otherLongTermAssets": 388,
        "otherReceivables": 0,
        "period": "2019-07-28",
        "propertyPlantEquipment": 1516,
        "retainedEarnings": 5984,
        "sharesOutstanding": 534,
        "shortTermDebt": 0,
        "shortTermInvestments": 14,
        "tangibleBookValueperShare": 4.4232,
        "totalAssets": 7955,
        "totalDebt": 250,
        "totalEquity": 5887,
        "totalLiabilities": 2068,
        "totalReceivables": 529
      },
      {
        "accountsPayable": 522,
        "accountsReceivables": 537,
        "accruedLiability": 506,
        "accumulatedDepreciation": -1678,
        "additionalPaidInCapital": 164,
        "cashEquivalents": 639,
        "cashShortTermInvestments": 646,
        "commonStock": 8,
        "currentAssets": 2251,
        "currentLiabilities": 1052,
        "deferredIncomeTax": 142,
        "goodwill": 2487,
        "intangiblesAssets": 1040,
        "inventory": 1031,
        "liabilitiesShareholdersEquity": 7936,
        "longTermDebt": 250,
        "longTermInvestments": 276,
        "minorityInterest": 4,
        "netDebt": -396,
        "otherAssets": 2487,
        "otherCurrentAssets": 36,
        "otherCurrentliabilities": 24,
        "otherEquity": -278,
        "otherLiabilities": 590,
        "otherLongTermAssets": 387,
        "otherReceivables": 1,
        "period": "2019-04-28",
        "propertyPlantEquipment": 1495,
        "retainedEarnings": 6004,
        "sharesOutstanding": 536,
        "shortTermDebt": 0,
        "shortTermInvestments": 7,
        "tangibleBookValueperShare": 4.4216,
        "totalAssets": 7936,
        "totalDebt": 250,
        "totalEquity": 5897,
        "totalLiabilities": 2038,
        "totalReceivables": 538
      },
      {
        "accountsPayable": 504,
        "accountsReceivables": 565,
        "accruedLiability": 492,
        "accumulatedDepreciation": -1647,
        "additionalPaidInCapital": 130,
        "cashEquivalents": 513,
        "cashShortTermInvestments": 513,
        "commonStock": 8,
        "currentAssets": 2101,
        "currentLiabilities": 1436,
        "currentPortionLongTermDebt": 375,
        "deferredIncomeTax": 180,
        "goodwill": 2717,
        "intangiblesAssets": 1205,
        "inventory": 994,
        "liabilitiesShareholdersEquity": 8155,
        "longTermDebt": 250,
        "longTermInvestments": 278,
        "minorityInterest": 4,
        "netDebt": 112,
        "otherAssets": 2717,
        "otherCurrentAssets": 29,
        "otherCurrentliabilities": 65,
        "otherEquity": -292,
        "otherLiabilities": 584,
        "otherLongTermAssets": 371,
        "otherReceivables": 0,
        "period": "2019-01-27",
        "propertyPlantEquipment": 1484,
        "retainedEarnings": 5856,
        "sharesOutstanding": 534,
        "shortTermDebt": 0,
        "tangibleBookValueperShare": 3.3333,
        "totalAssets": 8155,
        "totalDebt": 625,
        "totalEquity": 5702,
        "totalLiabilities": 2454,
        "totalReceivables": 565
      },
      {
        "accountsPayable": 619,
        "accountsReceivables": 600,
        "accruedLiability": 518,
        "accumulatedDepreciation": -1689,
        "additionalPaidInCapital": 107,
        "cashEquivalents": 459,
        "cashShortTermInvestments": 459,
        "commonStock": 8,
        "currentAssets": 2050,
        "currentLiabilities": 1139,
        "deferredIncomeTax": 197,
        "goodwill": 2714,
        "intangiblesAssets": 1207,
        "inventory": 964,
        "liabilitiesShareholdersEquity": 8142,
        "longTermDebt": 625,
        "longTermInvestments": 273,
        "minorityInterest": 4,
        "netDebt": 166,
        "otherAssets": 2714,
        "otherCurrentAssets": 23,
        "otherCurrentliabilities": 2,
        "otherEquity": -243,
        "otherLiabilities": 577,
        "otherLongTermAssets": 385,
        "otherReceivables": 4,
        "period": "2018-10-28",
        "propertyPlantEquipment": 1513,
        "retainedEarnings": 5730,
        "sharesOutstanding": 534,
        "shortTermDebt": 0,
        "tangibleBookValueperShare": 3.1461,
        "totalAssets": 8142,
        "totalDebt": 625,
        "totalEquity": 5601,
        "totalLiabilities": 2541,
        "totalReceivables": 604
      },
      {
        "accountsPayable": 489,
        "accountsReceivables": 559,
        "accruedLiability": 510,
        "accumulatedDepreciation": -1663,
        "additionalPaidInCapital": 28,
        "cashEquivalents": 269,
        "cashShortTermInvestments": 269,
        "commonStock": 8,
        "currentAssets": 1854,
        "currentLiabilities": 1097,
        "deferredIncomeTax": 139,
        "goodwill": 2735,
        "intangiblesAssets": 1237,
        "inventory": 1001,
        "liabilitiesShareholdersEquity": 7895,
        "longTermDebt": 625,
        "longTermInvestments": 276,
        "minorityInterest": 4,
        "netDebt": 451,
        "otherAssets": 2735,
        "otherCurrentAssets": 21,
        "otherCurrentliabilities": 2,
        "otherEquity": -259,
        "otherLiabilities": 639,
        "otherLongTermAssets": 383,
        "otherReceivables": 5,
        "period": "2018-07-29",
        "propertyPlantEquipment": 1410,
        "retainedEarnings": 5615,
        "sharesOutstanding": 531,
        "shortTermDebt": 95,
        "tangibleBookValueperShare": 2.6742,
        "totalAssets": 7895,
        "totalDebt": 720,
        "totalEquity": 5392,
        "totalLiabilities": 2504,
        "totalReceivables": 564
      },
      {
        "accountsPayable": 466,
        "accountsReceivables": 551,
        "accruedLiability": 496,
        "accumulatedDepreciation": -1633,
        "additionalPaidInCapital": 11,
        "cashEquivalents": 262,
        "cashShortTermInvestments": 262,
        "commonStock": 8,
        "currentAssets": 1851,
        "currentLiabilities": 1148,
        "deferredIncomeTax": 125,
        "goodwill": 2732,
        "intangiblesAssets": 1251,
        "inventory": 1011,
        "liabilitiesShareholdersEquity": 7830,
        "longTermDebt": 625,
        "longTermInvestments": 266,
        "minorityInterest": 4,
        "netDebt": 548,
        "otherAssets": 2732,
        "otherCurrentAssets": 24,
        "otherCurrentliabilities": 1,
        "otherEquity": -236,
        "otherLiabilities": 639,
        "otherLongTermAssets": 376,
        "otherReceivables": 3,
        "period": "2018-04-29",
        "propertyPlantEquipment": 1354,
        "retainedEarnings": 5504,
        "sharesOutstanding": 530,
        "shortTermDebt": 185,
        "tangibleBookValueperShare": 2.4604,
        "totalAssets": 7830,
        "totalDebt": 810,
        "totalEquity": 5287,
        "totalLiabilities": 2543,
        "totalReceivables": 554
      },
      {
        "accountsPayable": 533,
        "accountsReceivables": 569,
        "accruedLiability": 489,
        "accumulatedDepreciation": -1600,
        "additionalPaidInCapital": 19,
        "cashEquivalents": 386,
        "cashShortTermInvestments": 386,
        "commonStock": 8,
        "currentAssets": 1948,
        "currentLiabilities": 1324,
        "deferredIncomeTax": 115,
        "goodwill": 2957,
        "intangiblesAssets": 1023,
        "inventory": 973,
        "liabilitiesShareholdersEquity": 7859,
        "longTermDebt": 625,
        "longTermInvestments": 262,
        "minorityInterest": 4,
        "netDebt": 494,
        "otherAssets": 2957,
        "otherCurrentAssets": 20,
        "otherCurrentliabilities": 46,
        "otherEquity": -242,
        "otherLiabilities": 641,
        "otherLongTermAssets": 375,
        "otherReceivables": 0,
        "period": "2018-01-28",
        "propertyPlantEquipment": 1293,
        "retainedEarnings": 5367,
        "sharesOutstanding": 530,
        "shortTermDebt": 255,
        "tangibleBookValueperShare": 2.2094,
        "totalAssets": 7859,
        "totalDebt": 880,
        "totalEquity": 5151,
        "totalLiabilities": 2708,
        "totalReceivables": 569
      },
      {
        "accountsPayable": 553,
        "accountsReceivables": 618,
        "accruedLiability": 505,
        "accumulatedDepreciation": -1573,
        "additionalPaidInCapital": 14,
        "cashEquivalents": 444,
        "cashShortTermInvestments": 444,
        "commonStock": 8,
        "currentAssets": 2027,
        "currentLiabilities": 1058,
        "deferredIncomeTax": 98,
        "goodwill": 2120,
        "intangiblesAssets": 1027,
        "inventory": 921,
        "liabilitiesShareholdersEquity": 6976,
        "longTermDebt": 250,
        "longTermInvestments": 242,
        "minorityInterest": 4,
        "netDebt": -194,
        "otherAssets": 2120,
        "otherCurrentAssets": 21,
        "otherCurrentliabilities": 1,
        "otherEquity": -248,
        "otherLiabilities": 630,
        "otherLongTermAssets": 357,
        "otherReceivables": 23,
        "period": "2017-10-29",
        "propertyPlantEquipment": 1203,
        "retainedEarnings": 5163,
        "sharesOutstanding": 528,
        "shortTermDebt": 0,
        "tangibleBookValueperShare": 3.3883,
        "totalAssets": 6976,
        "totalDebt": 250,
        "totalEquity": 4936,
        "totalLiabilities": 2040,
        "totalReceivables": 641
      },
      {
        "accountsPayable": 421,
        "accountsReceivables": 549,
        "accruedLiability": 455,
        "accumulatedDepreciation": -1568,
        "additionalPaidInCapital": 0,
        "cashEquivalents": 633,
        "cashShortTermInvestments": 633,
        "commonStock": 8,
        "currentAssets": 2217,
        "currentLiabilities": 878,
        "deferredIncomeTax": 10,
        "goodwill": 1823,
        "intangiblesAssets": 883,
        "inventory": 1013,
        "liabilitiesShareholdersEquity": 6508,
        "longTermDebt": 250,
        "longTermInvestments": 248,
        "minorityInterest": 3,
        "netDebt": -383,
        "otherAssets": 1823,
        "otherCurrentAssets": 21,
        "otherCurrentliabilities": 2,
        "otherEquity": -292,
        "otherLiabilities": 617,
        "otherLongTermAssets": 283,
        "otherReceivables": 0,
        "period": "2017-07-30",
        "propertyPlantEquipment": 1054,
        "retainedEarnings": 5034,
        "sharesOutstanding": 528,
        "shortTermDebt": 0,
        "tangibleBookValueperShare": 3.8712,
        "totalAssets": 6508,
        "totalDebt": 250,
        "totalEquity": 4750,
        "totalLiabilities": 1758,
        "totalReceivables": 549
      },
      {
        "accountsPayable": 372,
        "accountsReceivables": 525,
        "accruedLiability": 451,
        "accumulatedDepreciation": -1545,
        "additionalPaidInCapital": 0,
        "cashEquivalents": 549,
        "cashShortTermInvestments": 549,
        "commonStock": 8,
        "currentAssets": 2126,
        "currentLiabilities": 825,
        "deferredIncomeTax": 8,
        "goodwill": 1823,
        "intangiblesAssets": 885,
        "inventory": 988,
        "liabilitiesShareholdersEquity": 6386,
        "longTermDebt": 250,
        "longTermInvestments": 247,
        "minorityInterest": 3,
        "netDebt": -299,
        "otherAssets": 1823,
        "otherCurrentAssets": 21,
        "otherCurrentliabilities": 2,
        "otherEquity": -299,
        "otherLiabilities": 617,
        "otherLongTermAssets": 262,
        "otherReceivables": 42,
        "period": "2017-04-30",
        "propertyPlantEquipment": 1044,
        "retainedEarnings": 4975,
        "sharesOutstanding": 529,
        "shortTermDebt": 0,
        "tangibleBookValueperShare": 3.7335,
        "totalAssets": 6386,
        "totalDebt": 250,
        "totalEquity": 4683,
        "totalLiabilities": 1703,
        "totalReceivables": 567
      },
      {
        "accountsPayable": 388,
        "accountsReceivables": 531,
        "accruedLiability": 467,
        "accumulatedDepreciation": -1523,
        "additionalPaidInCapital": 0,
        "cashEquivalents": 610,
        "cashShortTermInvestments": 610,
        "commonStock": 8,
        "currentAssets": 2120,
        "currentLiabilities": 920,
        "deferredIncomeTax": 6,
        "goodwill": 1823,
        "intangiblesAssets": 887,
        "inventory": 958,
        "liabilitiesShareholdersEquity": 6366,
        "longTermDebt": 250,
        "longTermInvestments": 244,
        "minorityInterest": 3,
        "netDebt": -360,
        "otherAssets": 1823,
        "otherCurrentAssets": 20,
        "otherCurrentliabilities": 65,
        "otherEquity": -302,
        "otherLiabilities": 615,
        "otherLongTermAssets": 258,
        "otherReceivables": 0,
        "period": "2017-01-29",
        "propertyPlantEquipment": 1035,
        "retainedEarnings": 4866,
        "sharesOutstanding": 529,
        "shortTermDebt": 0,
        "tangibleBookValueperShare": 3.5198,
        "totalAssets": 6366,
        "totalDebt": 250,
        "totalEquity": 4572,
        "totalLiabilities": 1794,
        "totalReceivables": 531
      },
      {
        "accountsPayable": 482,
        "accountsReceivables": 591,
        "accruedLiability": 567,
        "accumulatedDepreciation": -1662,
        "additionalPaidInCapital": 0,
        "cashEquivalents": 415,
        "cashShortTermInvestments": 415,
        "commonStock": 8,
        "currentAssets": 2030,
        "currentLiabilities": 1053,
        "deferredIncomeTax": 0,
        "goodwill": 1834,
        "intangiblesAssets": 903,
        "inventory": 986,
        "liabilitiesShareholdersEquity": 6370,
        "longTermDebt": 250,
        "longTermInvestments": 240,
        "minorityInterest": 3,
        "netDebt": -165,
        "otherAssets": 1834,
        "otherCurrentAssets": 20,
        "otherCurrentliabilities": 4,
        "otherEquity": -296,
        "otherLiabilities": 615,
        "otherLongTermAssets": 257,
        "otherReceivables": 19,
        "period": "2016-10-30",
        "propertyPlantEquipment": 1105,
        "retainedEarnings": 4737,
        "sharesOutstanding": 528,
        "shortTermDebt": 0,
        "tangibleBookValueperShare": 3.2405,
        "totalAssets": 6370,
        "totalDebt": 250,
        "totalEquity": 4448,
        "totalLiabilities": 1922,
        "totalReceivables": 610
      },
      {
        "accountsPayable": 415,
        "accountsReceivables": 565,
        "accruedLiability": 562,
        "accumulatedDepreciation": -1643,
        "additionalPaidInCapital": 0,
        "cashEquivalents": 380,
        "cashShortTermInvestments": 380,
        "commonStock": 8,
        "currentAssets": 2010,
        "currentLiabilities": 1129,
        "deferredIncomeTax": 0,
        "goodwill": 1922,
        "intangiblesAssets": 815,
        "inventory": 1034,
        "liabilitiesShareholdersEquity": 6388,
        "longTermDebt": 250,
        "longTermInvestments": 257,
        "minorityInterest": 3,
        "netDebt": 15,
        "otherAssets": 1922,
        "otherCurrentAssets": 24,
        "otherCurrentliabilities": 7,
        "otherEquity": -224,
        "otherLiabilities": 616,
        "otherLongTermAssets": 331,
        "otherReceivables": 7,
        "period": "2016-07-24",
        "propertyPlantEquipment": 1053,
        "retainedEarnings": 4607,
        "sharesOutstanding": 529,
        "shortTermDebt": 145,
        "tangibleBookValueperShare": 3.1267,
        "totalAssets": 6388,
        "totalDebt": 395,
        "totalEquity": 4391,
        "totalLiabilities": 1998,
        "totalReceivables": 572
      },
      {
        "accountsPayable": 389,
        "accountsReceivables": 548,
        "accruedLiability": 538,
        "accumulatedDepreciation": -1683,
        "additionalPaidInCapital": 11,
        "cashEquivalents": 380,
        "cashShortTermInvestments": 380,
        "commonStock": 8,
        "currentAssets": 1975,
        "currentLiabilities": 937,
        "deferredIncomeTax": 0,
        "goodwill": 1698,
        "intangiblesAssets": 823,
        "inventory": 1027,
        "liabilitiesShareholdersEquity": 6110,
        "longTermDebt": 250,
        "longTermInvestments": 255,
        "minorityInterest": 3,
        "netDebt": -130,
        "otherAssets": 1698,
        "otherCurrentAssets": 19,
        "otherCurrentliabilities": 10,
        "otherEquity": -226,
        "otherLiabilities": 613,
        "otherLongTermAssets": 310,
        "otherReceivables": 0,
        "period": "2016-04-24",
        "propertyPlantEquipment": 1049,
        "retainedEarnings": 4513,
        "sharesOutstanding": 530,
        "shortTermDebt": 0,
        "tangibleBookValueperShare": 3.3679,
        "totalAssets": 6110,
        "totalDebt": 250,
        "totalEquity": 4306,
        "totalLiabilities": 1804,
        "totalReceivables": 548
      },
      {
        "accountsPayable": 411,
        "accountsReceivables": 555,
        "accruedLiability": 519,
        "accumulatedDepreciation": -1659,
        "additionalPaidInCapital": 6,
        "cashEquivalents": 375,
        "cashShortTermInvestments": 375,
        "commonStock": 8,
        "currentAssets": 1946,
        "currentLiabilities": 1020,
        "goodwill": 1699,
        "intangiblesAssets": 825,
        "inventory": 995,
        "liabilitiesShareholdersEquity": 6041,
        "longTermDebt": 250,
        "longTermInvestments": 254,
        "minorityInterest": 3,
        "netDebt": -125,
        "otherAssets": 1699,
        "otherCurrentAssets": 21,
        "otherCurrentliabilities": 90,
        "otherEquity": -228,
        "otherLiabilities": 607,
        "otherLongTermAssets": 303,
        "otherReceivables": 0,
        "period": "2016-01-24",
        "propertyPlantEquipment": 1014,
        "retainedEarnings": 4375,
        "sharesOutstanding": 529,
        "shortTermDebt": 0,
        "tangibleBookValueperShare": 3.0926,
        "totalAssets": 6041,
        "totalDebt": 250,
        "totalEquity": 4160,
        "totalLiabilities": 1881,
        "totalReceivables": 555
      },
      {
        "accountsPayable": 495,
        "accountsReceivables": 606,
        "accruedLiability": 527,
        "accumulatedDepreciation": -1634,
        "cashEquivalents": 347,
        "cashShortTermInvestments": 347,
        "commonStock": 8,
        "currentAssets": 2063,
        "currentLiabilities": 1214,
        "deferredIncomeTax": 64,
        "goodwill": 1699,
        "intangiblesAssets": 827,
        "inventory": 993,
        "liabilitiesShareholdersEquity": 6140,
        "longTermDebt": 250,
        "longTermInvestments": 259,
        "minorityInterest": 3,
        "netDebt": 88,
        "otherAssets": 1699,
        "otherCurrentAssets": 110,
        "otherCurrentliabilities": 7,
        "otherEquity": -226,
        "otherLiabilities": 610,
        "otherLongTermAssets": 279,
        "otherReceivables": 6,
        "period": "2015-10-25",
        "propertyPlantEquipment": 1012,
        "retainedEarnings": 4216,
        "sharesOutstanding": 528,
        "shortTermDebt": 185,
        "tangibleBookValueperShare": 2.7879,
        "totalAssets": 6140,
        "totalDebt": 435,
        "totalEquity": 3998,
        "totalLiabilities": 2142,
        "totalReceivables": 612
      }
    ],
    "symbol": "HRL"
  }
}