{
  "symbol": "MS",
  "data_type": "company_profile",
  "timestamp": "2025-09-19T14:49:43.790016",
  "data": {
    "address": "1585 Broadway",
    "alias": null,
    "city": "New York City",
    "country": "US",
    "currency": "USD",
    "cusip": "617446448",
    "description": "Morgan Stanley operates as a global financial services company. The company is headquartered in New York City, New York and currently employs 80,000 full-time employees.  The firm is engaged in providing a range of investment banking, securities, wealth management and investment management services. Its segments include Institutional Securities, Wealth Management and Investment Management. Its Institutional Securities segment provides a variety of products and services to corporations, governments, financial institutions and ultra-high net worth clients. Its Wealth Management segment provides an array of financial services and solutions to individual investors and small to medium-sized businesses and institutions. Its Investment Management segment provides a range of investment strategies and products that span geographies, asset classes, and public and private markets to a diverse group of clients across institutional and intermediary channels. Its investment banking services consist of capital raising and financial advisory services, including the underwriting of debt and other products.",
    "employeeTotal": 80000,
    "estimateCurrency": "USD",
    "exchange": "NEW YORK STOCK EXCHANGE, INC.",
    "finnhubIndustry": "Financial Services",
    "floatingShare": 1215.22,
    "fundamentalFreq": "q",
    "ggroup": "Financial Services",
    "gind": "Capital Markets",
    "gsector": "Financials",
    "gsubind": "Investment Banking & Brokerage",
    "insiderOwnership": 0.1965,
    "institutionOwnership": 63.0226,
    "ipo": "1986-03-21",
    "irUrl": "https://www.morganstanley.com/about-us-ir/",
    "isin": "US6174464486",
    "lei": "IGJSJL3JD5P30I6NJZ34",
    "logo": "https://static2.finnhub.io/file/publicdatany/finnhubimage/stock_logo/MS.svg",
    "marketCapCurrency": "USD",
    "marketCapitalization": 254200.50172481497,
    "marketcapUSD": 0,
    "naics": "Securities and Commodity Contracts Intermediation and Brokerage",
    "naicsNationalIndustry": "Investment Banking and Securities Intermediation",
    "naicsSector": "Finance and Insurance",
    "naicsSubsector": "Securities, Commodity Contracts, and Other Financial Investments and Related Activities",
    "name": "Morgan Stanley",
    "phone": "12127614000",
    "sedol": "2262314",
    "shareOutstanding": 1596.34,
    "state": "NEW YORK",
    "ticker": "MS",
    "usShare": 0,
    "weburl": "https://www.morganstanley.com/"
  }
}