{
  "symbol": "CNP",
  "data_type": "company_profile",
  "timestamp": "2025-09-19T14:48:45.163511",
  "data": {
    "address": "1111 Louisiana St.",
    "alias": null,
    "city": "Houston",
    "country": "US",
    "currency": "USD",
    "cusip": "15189T107",
    "description": "CenterPoint Energy, Inc. is a holding company, which engages in the business of power generation and distribution. The company is headquartered in Houston, Texas and currently employs 8,872 full-time employees.  The Company, through its subsidiaries, owns and operates electric transmission, distribution and generation facilities and natural gas distribution systems. Its segments include Electric and Natural Gas. The Electric segment includes electric transmission and distribution services that are subject to rate regulation in Houston Electric's and Indiana Electric's service territories. The Natural Gas segment includes intrastate natural gas sales to, and natural gas transportation and distribution for residential, commercial, industrial and institutional customers in Indiana, Minnesota, Ohio, and Texas; permanent pipeline connections through interconnects with various interstate and intrastate pipeline companies; and home appliance maintenance and repair services to customers in Minnesota and home repair protection plans to natural gas customers in Indiana, Ohio and Texas through a third party.",
    "employeeTotal": 8872,
    "estimateCurrency": "USD",
    "exchange": "NEW YORK STOCK EXCHANGE, INC.",
    "finnhubIndustry": "Utilities",
    "floatingShare": 649.83,
    "fundamentalFreq": "q",
    "ggroup": "Utilities",
    "gind": "Multi-Utilities",
    "gsector": "Utilities",
    "gsubind": "Multi-Utilities",
    "insiderOwnership": 0.1513,
    "institutionOwnership": 106.4864,
    "ipo": "1943-08-16",
    "irUrl": "https://investors.centerpointenergy.com/",
    "isin": "US15189T1079",
    "lei": "",
    "logo": "https://static2.finnhub.io/file/publicdatany/finnhubimage/stock_logo/CNP.svg",
    "marketCapCurrency": "USD",
    "marketCapitalization": 24854.565033101706,
    "marketcapUSD": 0,
    "naics": "Natural Gas Distribution",
    "naicsNationalIndustry": "Natural Gas Distribution",
    "naicsSector": "Utilities",
    "naicsSubsector": "Utilities",
    "name": "CenterPoint Energy Inc",
    "phone": "17132073000",
    "sedol": "2440637",
    "shareOutstanding": 652.86,
    "state": "TEXAS",
    "ticker": "CNP",
    "usShare": 0,
    "weburl": "https://www.centerpointenergy.com/"
  }
}